[{"elapsed_time":177329,"segment":1,"source_type":4,"start_time":1649455142853},{"elapsed_time":177329,"segment":1,"source_type":4,"start_time":1649455142853},{"elapsed_time":180329,"segment":1,"source_type":4,"start_time":1649455145853},{"elapsed_time":190329,"segment":1,"source_type":4,"start_time":1649455155853},{"elapsed_time":200329,"segment":1,"source_type":4,"start_time":1649455165853},{"elapsed_time":210329,"segment":1,"source_type":4,"start_time":1649455175853},{"elapsed_time":240329,"segment":1,"source_type":4,"start_time":1649455205853},{"elapsed_time":300330,"segment":1,"source_type":4,"start_time":1649455265854},{"elapsed_time":360330,"segment":1,"source_type":4,"start_time":1649455325854},{"elapsed_time":420819,"segment":1,"source_type":4,"start_time":1649455386343},{"elapsed_time":480819,"segment":1,"source_type":4,"start_time":1649455446343},{"elapsed_time":540819,"segment":1,"source_type":4,"start_time":1649455506343},{"elapsed_time":600016,"segment":1,"source_type":4,"start_time":1649455565540},{"elapsed_time":660911,"segment":1,"source_type":4,"start_time":1649455626436},{"elapsed_time":720911,"segment":1,"source_type":4,"start_time":1649455686436},{"elapsed_time":780911,"segment":1,"source_type":4,"start_time":1649455746436},{"elapsed_time":840911,"segment":1,"source_type":4,"start_time":1649455806436},{"elapsed_time":900911,"segment":1,"source_type":4,"start_time":1649455866436},{"elapsed_time":960912,"segment":1,"source_type":4,"start_time":1649455926436},{"elapsed_time":1000,"segment":1,"source_type":4,"start_time":1649454966525},{"elapsed_time":1000,"segment":1,"source_type":4,"start_time":1649454966524},{"elapsed_time":60000,"segment":1,"source_type":4,"start_time":1649455025525},{"elapsed_time":120000,"segment":1,"source_type":4,"start_time":1649455085525},{"elapsed_time":180000,"segment":1,"source_type":4,"start_time":1649455145525},{"elapsed_time":240000,"segment":1,"source_type":4,"start_time":1649455205525},{"elapsed_time":300000,"segment":1,"source_type":4,"start_time":1649455265525},{"elapsed_time":360000,"segment":1,"source_type":4,"start_time":1649455325524},{"elapsed_time":420000,"segment":1,"source_type":4,"start_time":1649455385524},{"elapsed_time":480000,"segment":1,"source_type":4,"start_time":1649455445525},{"elapsed_time":540000,"segment":1,"source_type":4,"start_time":1649455505525},{"elapsed_time":540000,"segment":1,"source_type":4,"start_time":1649455505524},{"elapsed_time":600000,"segment":1,"source_type":4,"start_time":1649455565525},{"elapsed_time":660000,"segment":1,"source_type":4,"start_time":1649455625524},{"elapsed_time":720000,"segment":1,"source_type":4,"start_time":1649455685525},{"elapsed_time":780000,"segment":1,"source_type":4,"start_time":1649455745525},{"elapsed_time":840000,"segment":1,"source_type":4,"start_time":1649455805524},{"elapsed_time":900000,"segment":1,"source_type":4,"start_time":1649455865524},{"elapsed_time":960000,"segment":1,"source_type":4,"start_time":1649455925525},{"elapsed_time":960000,"segment":1,"source_type":4,"start_time":1649455925525}]