[{"mCalorie":0.0,"mDistance":0.0,"mNowHealthyStep":0,"mRunStepCount":0,"mSpeed":0.0,"mStartTime":0,"mStepCount":0,"mTimeUnit":600000,"mTotalActiveTime":0.0,"mWalkStepCount":0},{"mCalorie":0.0,"mDistance":0.0,"mNowHealthyStep":0,"mRunStepCount":0,"mSpeed":0.0,"mStartTime":0,"mStepCount":0,"mTimeUnit":600000,"mTotalActiveTime":0.0,"mWalkStepCount":0},{"mCalorie":0.0,"mDistance":0.0,"mNowHealthyStep":0,"mRunStepCount":0,"mSpeed":0.0,"mStartTime":0,"mStepCount":0,"mTimeUnit":600000,"mTotalActiveTime":0.0,"mWalkStepCount":0},{"mCalorie":0.0,"mDistance":0.0,"mNowHealthyStep":0,"mRunStepCount":0,"mSpeed":0.0,"mStartTime":0,"mStepCount":0,"mTimeUnit":600000,"mTotalActiveTime":0.0,"mWalkStepCount":0},{"mCalorie":0.0,"mDistance":0.0,"mNowHealthyStep":0,"mRunStepCount":0,"mSpeed":0.0,"mStartTime":0,"mStepCount":0,"mTimeUnit":600000,"mTotalActiveTime":0.0,"mWalkStepCount":0},{"mCalorie":0.0,"mDistance":0.0,"mNowHealthyStep":0,"mRunStepCount":0,"mSpeed":0.0,"mStartTime":0,"mStepCount":0,"mTimeUnit":600000,"mTotalActiveTime":0.0,"mWalkStepCount":0},{"mCalorie":0.0,"mDistance":0.0,"mNowHealthyStep":0,"mRunStepCount":0,"mSpeed":0.0,"mStartTime":0,"mStepCount":0,"mTimeUnit":600000,"mTotalActiveTime":0.0,"mWalkStepCount":0},{"mCalorie":0.0,"mDistance":0.0,"mNowHealthyStep":0,"mRunStepCount":0,"mSpeed":0.0,"mStartTime":0,"mStepCount":0,"mTimeUnit":600000,"mTotalActiveTime":0.0,"mWalkStepCount":0},{"mCalorie":0.0,"mDistance":0.0,"mNowHealthyStep":0,"mRunStepCount":0,"mSpeed":0.0,"mStartTime":0,"mStepCount":0,"mTimeUnit":600000,"mTotalActiveTime":0.0,"mWalkStepCount":0},{"mCalorie":0.0,"mDistance":0.0,"mNowHealthyStep":0,"mRunStepCount":0,"mSpeed":0.0,"mStartTime":0,"mStepCount":0,"mTimeUnit":600000,"mTotalActiveTime":0.0,"mWalkStepCount":0},{"mCalorie":0.0,"mDistance":0.0,"mNowHealthyStep":0,"mRunStepCount":0,"mSpeed":0.0,"mStartTime":0,"mStepCount":0,"mTimeUnit":600000,"mTotalActiveTime":0.0,"mWalkStepCount":0},{"mCalorie":0.0,"mDistance":0.0,"mNowHealthyStep":0,"mRunStepCount":0,"mSpeed":0.0,"mStartTime":0,"mStepCount":0,"mTimeUnit":600000,"mTotalActiveTime":0.0,"mWalkStepCount":0},{"mCalorie":0.0,"mDistance":0.0,"mNowHealthyStep":0,"mRunStepCount":0,"mSpeed":0.0,"mStartTime":0,"mStepCount":0,"mTimeUnit":600000,"mTotalActiveTime":0.0,"mWalkStepCount":0},{"mCalorie":0.0,"mDistance":0.0,"mNowHealthyStep":0,"mRunStepCount":0,"mSpeed":0.0,"mStartTime":0,"mStepCount":0,"mTimeUnit":600000,"mTotalActiveTime":0.0,"mWalkStepCount":0},{"mCalorie":0.0,"mDistance":0.0,"mNowHealthyStep":0,"mRunStepCount":0,"mSpeed":0.0,"mStartTime":0,"mStepCount":0,"mTimeUnit":600000,"mTotalActiveTime":0.0,"mWalkStepCount":0},{"mCalorie":0.0,"mDistance":0.0,"mNowHealthyStep":0,"mRunStepCount":0,"mSpeed":0.0,"mStartTime":0,"mStepCount":0,"mTimeUnit":600000,"mTotalActiveTime":0.0,"mWalkStepCount":0},{"mCalorie":0.0,"mDistance":0.0,"mNowHealthyStep":0,"mRunStepCount":0,"mSpeed":0.0,"mStartTime":0,"mStepCount":0,"mTimeUnit":600000,"mTotalActiveTime":0.0,"mWalkStepCount":0},{"mCalorie":0.0,"mDistance":0.0,"mNowHealthyStep":0,"mRunStepCount":0,"mSpeed":0.0,"mStartTime":0,"mStepCount":0,"mTimeUnit":600000,"mTotalActiveTime":0.0,"mWalkStepCount":0},{"mCalorie":0.0,"mDistance":0.0,"mNowHealthyStep":0,"mRunStepCount":0,"mSpeed":0.0,"mStartTime":0,"mStepCount":0,"mTimeUnit":600000,"mTotalActiveTime":0.0,"mWalkStepCount":0},{"mCalorie":0.0,"mDistance":0.0,"mNowHealthyStep":0,"mRunStepCount":0,"mSpeed":0.0,"mStartTime":0,"mStepCount":0,"mTimeUnit":600000,"mTotalActiveTime":0.0,"mWalkStepCount":0},{"mCalorie":0.0,"mDistance":0.0,"mNowHealthyStep":0,"mRunStepCount":0,"mSpeed":0.0,"mStartTime":0,"mStepCount":0,"mTimeUnit":600000,"mTotalActiveTime":0.0,"mWalkStepCount":0},{"mCalorie":0.0,"mDistance":0.0,"mNowHealthyStep":0,"mRunStepCount":0,"mSpeed":0.0,"mStartTime":0,"mStepCount":0,"mTimeUnit":600000,"mTotalActiveTime":0.0,"mWalkStepCount":0},{"mCalorie":0.0,"mDistance":0.0,"mNowHealthyStep":0,"mRunStepCount":0,"mSpeed":0.0,"mStartTime":0,"mStepCount":0,"mTimeUnit":600000,"mTotalActiveTime":0.0,"mWalkStepCount":0},{"mCalorie":0.0,"mDistance":0.0,"mNowHealthyStep":0,"mRunStepCount":0,"mSpeed":0.0,"mStartTime":0,"mStepCount":0,"mTimeUnit":600000,"mTotalActiveTime":0.0,"mWalkStepCount":0},{"mCalorie":0.0,"mDistance":0.0,"mNowHealthyStep":0,"mRunStepCount":0,"mSpeed":0.0,"mStartTime":0,"mStepCount":0,"mTimeUnit":600000,"mTotalActiveTime":0.0,"mWalkStepCount":0},{"mCalorie":0.0,"mDistance":0.0,"mNowHealthyStep":0,"mRunStepCount":0,"mSpeed":0.0,"mStartTime":0,"mStepCount":0,"mTimeUnit":600000,"mTotalActiveTime":0.0,"mWalkStepCount":0},{"mCalorie":0.0,"mDistance":0.0,"mNowHealthyStep":0,"mRunStepCount":0,"mSpeed":0.0,"mStartTime":0,"mStepCount":0,"mTimeUnit":600000,"mTotalActiveTime":0.0,"mWalkStepCount":0},{"mCalorie":0.0,"mDistance":0.0,"mNowHealthyStep":0,"mRunStepCount":0,"mSpeed":0.0,"mStartTime":0,"mStepCount":0,"mTimeUnit":600000,"mTotalActiveTime":0.0,"mWalkStepCount":0},{"mCalorie":0.0,"mDistance":0.0,"mNowHealthyStep":0,"mRunStepCount":0,"mSpeed":0.0,"mStartTime":0,"mStepCount":0,"mTimeUnit":600000,"mTotalActiveTime":0.0,"mWalkStepCount":0},{"mCalorie":0.0,"mDistance":0.0,"mNowHealthyStep":0,"mRunStepCount":0,"mSpeed":0.0,"mStartTime":0,"mStepCount":0,"mTimeUnit":600000,"mTotalActiveTime":0.0,"mWalkStepCount":0},{"mCalorie":0.0,"mDistance":0.0,"mNowHealthyStep":0,"mRunStepCount":0,"mSpeed":0.0,"mStartTime":0,"mStepCount":0,"mTimeUnit":600000,"mTotalActiveTime":0.0,"mWalkStepCount":0},{"mCalorie":0.0,"mDistance":0.0,"mNowHealthyStep":0,"mRunStepCount":0,"mSpeed":0.0,"mStartTime":0,"mStepCount":0,"mTimeUnit":600000,"mTotalActiveTime":0.0,"mWalkStepCount":0},{"mCalorie":0.0,"mDistance":0.0,"mNowHealthyStep":0,"mRunStepCount":0,"mSpeed":0.0,"mStartTime":0,"mStepCount":0,"mTimeUnit":600000,"mTotalActiveTime":0.0,"mWalkStepCount":0},{"mCalorie":0.0,"mDistance":0.0,"mNowHealthyStep":0,"mRunStepCount":0,"mSpeed":0.0,"mStartTime":0,"mStepCount":0,"mTimeUnit":600000,"mTotalActiveTime":0.0,"mWalkStepCount":0},{"mCalorie":0.0,"mDistance":0.0,"mNowHealthyStep":0,"mRunStepCount":0,"mSpeed":0.0,"mStartTime":0,"mStepCount":0,"mTimeUnit":600000,"mTotalActiveTime":0.0,"mWalkStepCount":0},{"mCalorie":0.0,"mDistance":0.0,"mNowHealthyStep":0,"mRunStepCount":0,"mSpeed":0.0,"mStartTime":0,"mStepCount":0,"mTimeUnit":600000,"mTotalActiveTime":0.0,"mWalkStepCount":0},{"mCalorie":0.0,"mDistance":0.0,"mNowHealthyStep":0,"mRunStepCount":0,"mSpeed":0.0,"mStartTime":0,"mStepCount":0,"mTimeUnit":600000,"mTotalActiveTime":0.0,"mWalkStepCount":0},{"mCalorie":0.0,"mDistance":0.0,"mNowHealthyStep":0,"mRunStepCount":0,"mSpeed":0.0,"mStartTime":0,"mStepCount":0,"mTimeUnit":600000,"mTotalActiveTime":0.0,"mWalkStepCount":0},{"mCalorie":0.0,"mDistance":0.0,"mNowHealthyStep":0,"mRunStepCount":0,"mSpeed":0.0,"mStartTime":0,"mStepCount":0,"mTimeUnit":600000,"mTotalActiveTime":0.0,"mWalkStepCount":0},{"mCalorie":0.0,"mDistance":0.0,"mNowHealthyStep":0,"mRunStepCount":0,"mSpeed":0.0,"mStartTime":0,"mStepCount":0,"mTimeUnit":600000,"mTotalActiveTime":0.0,"mWalkStepCount":0},{"mCalorie":0.0,"mDistance":0.0,"mNowHealthyStep":0,"mRunStepCount":0,"mSpeed":0.0,"mStartTime":0,"mStepCount":0,"mTimeUnit":600000,"mTotalActiveTime":0.0,"mWalkStepCount":0},{"mCalorie":0.0,"mDistance":0.0,"mNowHealthyStep":0,"mRunStepCount":0,"mSpeed":0.0,"mStartTime":0,"mStepCount":0,"mTimeUnit":600000,"mTotalActiveTime":0.0,"mWalkStepCount":0},{"mCalorie":0.0,"mDistance":0.0,"mNowHealthyStep":0,"mRunStepCount":0,"mSpeed":0.0,"mStartTime":0,"mStepCount":0,"mTimeUnit":600000,"mTotalActiveTime":0.0,"mWalkStepCount":0},{"mCalorie":0.0,"mDistance":0.0,"mNowHealthyStep":0,"mRunStepCount":0,"mSpeed":0.0,"mStartTime":0,"mStepCount":0,"mTimeUnit":600000,"mTotalActiveTime":0.0,"mWalkStepCount":0},{"mCalorie":0.0,"mDistance":0.0,"mNowHealthyStep":0,"mRunStepCount":0,"mSpeed":0.0,"mStartTime":0,"mStepCount":0,"mTimeUnit":600000,"mTotalActiveTime":0.0,"mWalkStepCount":0},{"mCalorie":0.0,"mDistance":0.0,"mNowHealthyStep":0,"mRunStepCount":0,"mSpeed":0.0,"mStartTime":0,"mStepCount":0,"mTimeUnit":600000,"mTotalActiveTime":0.0,"mWalkStepCount":0},{"mCalorie":0.0,"mDistance":0.0,"mNowHealthyStep":0,"mRunStepCount":0,"mSpeed":0.0,"mStartTime":0,"mStepCount":0,"mTimeUnit":600000,"mTotalActiveTime":0.0,"mWalkStepCount":0},{"mCalorie":0.0,"mDistance":0.0,"mNowHealthyStep":0,"mRunStepCount":0,"mSpeed":0.0,"mStartTime":0,"mStepCount":0,"mTimeUnit":600000,"mTotalActiveTime":0.0,"mWalkStepCount":0},{"mCalorie":0.0,"mDistance":0.0,"mNowHealthyStep":0,"mRunStepCount":0,"mSpeed":0.0,"mStartTime":0,"mStepCount":0,"mTimeUnit":600000,"mTotalActiveTime":0.0,"mWalkStepCount":0},{"mCalorie":0.0,"mDistance":0.0,"mNowHealthyStep":0,"mRunStepCount":0,"mSpeed":0.0,"mStartTime":0,"mStepCount":0,"mTimeUnit":600000,"mTotalActiveTime":0.0,"mWalkStepCount":0},{"mCalorie":0.0,"mDistance":0.0,"mNowHealthyStep":0,"mRunStepCount":0,"mSpeed":0.0,"mStartTime":0,"mStepCount":0,"mTimeUnit":600000,"mTotalActiveTime":0.0,"mWalkStepCount":0},{"mCalorie":0.0,"mDistance":0.0,"mNowHealthyStep":0,"mRunStepCount":0,"mSpeed":0.0,"mStartTime":0,"mStepCount":0,"mTimeUnit":600000,"mTotalActiveTime":0.0,"mWalkStepCount":0},{"mCalorie":0.0,"mDistance":0.0,"mNowHealthyStep":0,"mRunStepCount":0,"mSpeed":0.0,"mStartTime":0,"mStepCount":0,"mTimeUnit":600000,"mTotalActiveTime":0.0,"mWalkStepCount":0},{"mCalorie":0.0,"mDistance":0.0,"mNowHealthyStep":0,"mRunStepCount":0,"mSpeed":0.0,"mStartTime":0,"mStepCount":0,"mTimeUnit":600000,"mTotalActiveTime":0.0,"mWalkStepCount":0},{"mCalorie":0.0,"mDistance":0.0,"mNowHealthyStep":0,"mRunStepCount":0,"mSpeed":0.0,"mStartTime":0,"mStepCount":0,"mTimeUnit":600000,"mTotalActiveTime":0.0,"mWalkStepCount":0},{"mCalorie":0.0,"mDistance":0.0,"mNowHealthyStep":0,"mRunStepCount":0,"mSpeed":0.0,"mStartTime":0,"mStepCount":0,"mTimeUnit":600000,"mTotalActiveTime":0.0,"mWalkStepCount":0},{"mCalorie":0.0,"mDistance":0.0,"mNowHealthyStep":0,"mRunStepCount":0,"mSpeed":0.0,"mStartTime":0,"mStepCount":0,"mTimeUnit":600000,"mTotalActiveTime":0.0,"mWalkStepCount":0},{"mCalorie":0.0,"mDistance":0.0,"mNowHealthyStep":0,"mRunStepCount":0,"mSpeed":0.0,"mStartTime":0,"mStepCount":0,"mTimeUnit":600000,"mTotalActiveTime":0.0,"mWalkStepCount":0},{"mCalorie":0.0,"mDistance":0.0,"mNowHealthyStep":0,"mRunStepCount":0,"mSpeed":0.0,"mStartTime":0,"mStepCount":0,"mTimeUnit":600000,"mTotalActiveTime":0.0,"mWalkStepCount":0},{"mCalorie":0.0,"mDistance":0.0,"mNowHealthyStep":0,"mRunStepCount":0,"mSpeed":0.0,"mStartTime":0,"mStepCount":0,"mTimeUnit":600000,"mTotalActiveTime":0.0,"mWalkStepCount":0},{"mCalorie":0.0,"mDistance":0.0,"mNowHealthyStep":0,"mRunStepCount":0,"mSpeed":0.0,"mStartTime":0,"mStepCount":0,"mTimeUnit":600000,"mTotalActiveTime":0.0,"mWalkStepCount":0},{"mCalorie":0.0,"mDistance":0.0,"mNowHealthyStep":0,"mRunStepCount":0,"mSpeed":0.0,"mStartTime":0,"mStepCount":0,"mTimeUnit":600000,"mTotalActiveTime":0.0,"mWalkStepCount":0},{"mCalorie":1.449999988079071,"mDistance":26.139999866485596,"mNowHealthyStep":0,"mRunStepCount":0,"mSpeed":4.171178817749023,"mStartTime":0,"mStepCount":35,"mTimeUnit":600000,"mTotalActiveTime":22560.52869823818,"mWalkStepCount":35},{"mCalorie":0.0,"mDistance":0.0,"mNowHealthyStep":0,"mRunStepCount":0,"mSpeed":0.0,"mStartTime":0,"mStepCount":0,"mTimeUnit":600000,"mTotalActiveTime":0.0,"mWalkStepCount":0},{"mCalorie":0.0,"mDistance":0.0,"mNowHealthyStep":0,"mRunStepCount":0,"mSpeed":0.0,"mStartTime":0,"mStepCount":0,"mTimeUnit":600000,"mTotalActiveTime":0.0,"mWalkStepCount":0},{"mCalorie":0.0,"mDistance":0.0,"mNowHealthyStep":0,"mRunStepCount":0,"mSpeed":0.0,"mStartTime":0,"mStepCount":0,"mTimeUnit":600000,"mTotalActiveTime":0.0,"mWalkStepCount":0},{"mCalorie":0.7800000011920929,"mDistance":15.109999656677246,"mNowHealthyStep":0,"mRunStepCount":0,"mSpeed":5.767543792724609,"mStartTime":0,"mStepCount":19,"mTimeUnit":600000,"mTotalActiveTime":9431.397669250313,"mWalkStepCount":19},{"mCalorie":1.960000216960907,"mDistance":36.56000518798828,"mNowHealthyStep":0,"mRunStepCount":0,"mSpeed":4.61789083480835,"mStartTime":0,"mStepCount":48,"mTimeUnit":600000,"mTotalActiveTime":28501.326206697726,"mWalkStepCount":48},{"mCalorie":1.2099999785423279,"mDistance":21.6200008392334,"mNowHealthyStep":0,"mRunStepCount":0,"mSpeed":4.127494812011719,"mStartTime":0,"mStepCount":29,"mTimeUnit":600000,"mTotalActiveTime":18856.959611300164,"mWalkStepCount":29},{"mCalorie":7.639999985694885,"mDistance":141.2400026321411,"mNowHealthyStep":0,"mRunStepCount":0,"mSpeed":4.704329013824463,"mStartTime":0,"mStepCount":186,"mTimeUnit":600000,"mTotalActiveTime":108084.28414975056,"mWalkStepCount":186},{"mCalorie":0.0,"mDistance":0.0,"mNowHealthyStep":0,"mRunStepCount":0,"mSpeed":0.0,"mStartTime":0,"mStepCount":0,"mTimeUnit":600000,"mTotalActiveTime":0.0,"mWalkStepCount":0},{"mCalorie":0.0,"mDistance":0.0,"mNowHealthyStep":0,"mRunStepCount":0,"mSpeed":0.0,"mStartTime":0,"mStepCount":0,"mTimeUnit":600000,"mTotalActiveTime":0.0,"mWalkStepCount":0},{"mCalorie":0.0,"mDistance":0.0,"mNowHealthyStep":0,"mRunStepCount":0,"mSpeed":0.0,"mStartTime":0,"mStepCount":0,"mTimeUnit":600000,"mTotalActiveTime":0.0,"mWalkStepCount":0},{"mCalorie":1.4000001549720764,"mDistance":25.769999504089355,"mNowHealthyStep":0,"mRunStepCount":0,"mSpeed":4.641933917999268,"mStartTime":0,"mStepCount":34,"mTimeUnit":600000,"mTotalActiveTime":19985.635735670985,"mWalkStepCount":34},{"mCalorie":3.5199990272521973,"mDistance":67.55999517440796,"mNowHealthyStep":0,"mRunStepCount":0,"mSpeed":4.748251914978027,"mStartTime":0,"mStepCount":88,"mTimeUnit":600000,"mTotalActiveTime":51222.2150203253,"mWalkStepCount":88},{"mCalorie":0.0,"mDistance":0.0,"mNowHealthyStep":0,"mRunStepCount":0,"mSpeed":0.0,"mStartTime":0,"mStepCount":0,"mTimeUnit":600000,"mTotalActiveTime":0.0,"mWalkStepCount":0},{"mCalorie":0.0,"mDistance":0.0,"mNowHealthyStep":0,"mRunStepCount":0,"mSpeed":0.0,"mStartTime":0,"mStepCount":0,"mTimeUnit":600000,"mTotalActiveTime":0.0,"mWalkStepCount":0},{"mCalorie":0.0,"mDistance":0.0,"mNowHealthyStep":0,"mRunStepCount":0,"mSpeed":0.0,"mStartTime":0,"mStepCount":0,"mTimeUnit":600000,"mTotalActiveTime":0.0,"mWalkStepCount":0},{"mCalorie":0.0,"mDistance":0.0,"mNowHealthyStep":0,"mRunStepCount":0,"mSpeed":0.0,"mStartTime":0,"mStepCount":0,"mTimeUnit":600000,"mTotalActiveTime":0.0,"mWalkStepCount":0},{"mCalorie":0.0,"mDistance":0.0,"mNowHealthyStep":0,"mRunStepCount":0,"mSpeed":0.0,"mStartTime":0,"mStepCount":0,"mTimeUnit":600000,"mTotalActiveTime":0.0,"mWalkStepCount":0},{"mCalorie":0.0,"mDistance":0.0,"mNowHealthyStep":0,"mRunStepCount":0,"mSpeed":0.0,"mStartTime":0,"mStepCount":0,"mTimeUnit":600000,"mTotalActiveTime":0.0,"mWalkStepCount":0},{"mCalorie":0.37999996542930603,"mDistance":6.739999771118164,"mNowHealthyStep":0,"mRunStepCount":0,"mSpeed":4.476099014282227,"mStartTime":0,"mStepCount":9,"mTimeUnit":600000,"mTotalActiveTime":5420.791429904571,"mWalkStepCount":9},{"mCalorie":2.3999999165534973,"mDistance":43.39000129699707,"mNowHealthyStep":0,"mRunStepCount":0,"mSpeed":4.38912296295166,"mStartTime":0,"mStepCount":58,"mTimeUnit":600000,"mTotalActiveTime":35588.88890229,"mWalkStepCount":58},{"mCalorie":0.7300000190734863,"mDistance":13.64000129699707,"mNowHealthyStep":0,"mRunStepCount":0,"mSpeed":4.618279933929443,"mStartTime":0,"mStepCount":18,"mTimeUnit":600000,"mTotalActiveTime":10632.531022737187,"mWalkStepCount":18},{"mCalorie":0.0,"mDistance":0.0,"mNowHealthyStep":0,"mRunStepCount":0,"mSpeed":0.0,"mStartTime":0,"mStepCount":0,"mTimeUnit":600000,"mTotalActiveTime":0.0,"mWalkStepCount":0},{"mCalorie":1.6100002527236938,"mDistance":28.69999885559082,"mNowHealthyStep":0,"mRunStepCount":0,"mSpeed":4.026961803436279,"mStartTime":0,"mStepCount":39,"mTimeUnit":600000,"mTotalActiveTime":25657.058230500927,"mWalkStepCount":39},{"mCalorie":0.0,"mDistance":0.0,"mNowHealthyStep":0,"mRunStepCount":0,"mSpeed":0.0,"mStartTime":0,"mStepCount":0,"mTimeUnit":600000,"mTotalActiveTime":0.0,"mWalkStepCount":0},{"mCalorie":1.719999998807907,"mDistance":30.210000038146973,"mNowHealthyStep":0,"mRunStepCount":0,"mSpeed":4.014927864074707,"mStartTime":0,"mStepCount":41,"mTimeUnit":600000,"mTotalActiveTime":27087.909299575644,"mWalkStepCount":41},{"mCalorie":0.8699999749660492,"mDistance":15.550000190734863,"mNowHealthyStep":0,"mRunStepCount":0,"mSpeed":3.9771628379821777,"mStartTime":0,"mStepCount":21,"mTimeUnit":600000,"mTotalActiveTime":14075.360213035568,"mWalkStepCount":21},{"mCalorie":0.0,"mDistance":0.0,"mNowHealthyStep":0,"mRunStepCount":0,"mSpeed":0.0,"mStartTime":0,"mStepCount":0,"mTimeUnit":600000,"mTotalActiveTime":0.0,"mWalkStepCount":0},{"mCalorie":0.0,"mDistance":0.0,"mNowHealthyStep":0,"mRunStepCount":0,"mSpeed":0.0,"mStartTime":0,"mStepCount":0,"mTimeUnit":600000,"mTotalActiveTime":0.0,"mWalkStepCount":0},{"mCalorie":0.0,"mDistance":0.0,"mNowHealthyStep":0,"mRunStepCount":0,"mSpeed":0.0,"mStartTime":0,"mStepCount":0,"mTimeUnit":600000,"mTotalActiveTime":0.0,"mWalkStepCount":0},{"mCalorie":0.0,"mDistance":0.0,"mNowHealthyStep":0,"mRunStepCount":0,"mSpeed":0.0,"mStartTime":0,"mStepCount":0,"mTimeUnit":600000,"mTotalActiveTime":0.0,"mWalkStepCount":0},{"mCalorie":0.0,"mDistance":0.0,"mNowHealthyStep":0,"mRunStepCount":0,"mSpeed":0.0,"mStartTime":0,"mStepCount":0,"mTimeUnit":600000,"mTotalActiveTime":0.0,"mWalkStepCount":0},{"mCalorie":0.0,"mDistance":0.0,"mNowHealthyStep":0,"mRunStepCount":0,"mSpeed":0.0,"mStartTime":0,"mStepCount":0,"mTimeUnit":600000,"mTotalActiveTime":0.0,"mWalkStepCount":0},{"mCalorie":0.0,"mDistance":0.0,"mNowHealthyStep":0,"mRunStepCount":0,"mSpeed":0.0,"mStartTime":0,"mStepCount":0,"mTimeUnit":600000,"mTotalActiveTime":0.0,"mWalkStepCount":0},{"mCalorie":0.0,"mDistance":0.0,"mNowHealthyStep":0,"mRunStepCount":0,"mSpeed":0.0,"mStartTime":0,"mStepCount":0,"mTimeUnit":600000,"mTotalActiveTime":0.0,"mWalkStepCount":0},{"mCalorie":0.0,"mDistance":0.0,"mNowHealthyStep":0,"mRunStepCount":0,"mSpeed":0.0,"mStartTime":0,"mStepCount":0,"mTimeUnit":600000,"mTotalActiveTime":0.0,"mWalkStepCount":0},{"mCalorie":0.0,"mDistance":0.0,"mNowHealthyStep":0,"mRunStepCount":0,"mSpeed":0.0,"mStartTime":0,"mStepCount":0,"mTimeUnit":600000,"mTotalActiveTime":0.0,"mWalkStepCount":0},{"mCalorie":0.6800000071525574,"mDistance":11.819999694824219,"mNowHealthyStep":0,"mRunStepCount":0,"mSpeed":4.0,"mStartTime":0,"mStepCount":16,"mTimeUnit":600000,"mTotalActiveTime":10637.999725341797,"mWalkStepCount":16},{"mCalorie":0.9500001668930054,"mDistance":17.039997100830078,"mNowHealthyStep":0,"mRunStepCount":0,"mSpeed":4.062028884887695,"mStartTime":0,"mStepCount":23,"mTimeUnit":600000,"mTotalActiveTime":15101.810277915903,"mWalkStepCount":23},{"mCalorie":0.0,"mDistance":0.0,"mNowHealthyStep":0,"mRunStepCount":0,"mSpeed":0.0,"mStartTime":0,"mStepCount":0,"mTimeUnit":600000,"mTotalActiveTime":0.0,"mWalkStepCount":0},{"mCalorie":0.0,"mDistance":0.0,"mNowHealthyStep":0,"mRunStepCount":0,"mSpeed":0.0,"mStartTime":0,"mStepCount":0,"mTimeUnit":600000,"mTotalActiveTime":0.0,"mWalkStepCount":0},{"mCalorie":0.0,"mDistance":0.0,"mNowHealthyStep":0,"mRunStepCount":0,"mSpeed":0.0,"mStartTime":0,"mStepCount":0,"mTimeUnit":600000,"mTotalActiveTime":0.0,"mWalkStepCount":0},{"mCalorie":0.5299999713897705,"mDistance":10.0600004196167,"mNowHealthyStep":0,"mRunStepCount":0,"mSpeed":5.299999713897705,"mStartTime":0,"mStepCount":13,"mTimeUnit":600000,"mTotalActiveTime":6833.208201059749,"mWalkStepCount":13},{"mCalorie":0.0,"mDistance":0.0,"mNowHealthyStep":0,"mRunStepCount":0,"mSpeed":0.0,"mStartTime":0,"mStepCount":0,"mTimeUnit":600000,"mTotalActiveTime":0.0,"mWalkStepCount":0},{"mCalorie":0.6899999976158142,"mDistance":11.65999984741211,"mNowHealthyStep":0,"mRunStepCount":0,"mSpeed":3.799999952316284,"mStartTime":0,"mStepCount":16,"mTimeUnit":600000,"mTotalActiveTime":11046.315783529732,"mWalkStepCount":16},{"mCalorie":43.04999399185181,"mDistance":837.5398864746094,"mNowHealthyStep":0,"mRunStepCount":0,"mSpeed":5.3407158851623535,"mStartTime":0,"mStepCount":1075,"mTimeUnit":600000,"mTotalActiveTime":564557.92181635,"mWalkStepCount":1075},{"mCalorie":32.83999541401863,"mDistance":633.3098974227905,"mNowHealthyStep":0,"mRunStepCount":0,"mSpeed":5.121262073516846,"mStartTime":0,"mStepCount":820,"mTimeUnit":600000,"mTotalActiveTime":445186.3011090588,"mWalkStepCount":820},{"mCalorie":55.889999598264694,"mDistance":788.0699915885925,"mNowHealthyStep":0,"mRunStepCount":376,"mSpeed":10.594744682312012,"mStartTime":0,"mStepCount":695,"mTimeUnit":600000,"mTotalActiveTime":267779.16838487436,"mWalkStepCount":319},{"mCalorie":114.23999905586243,"mDistance":1530.7599964141846,"mNowHealthyStep":0,"mRunStepCount":859,"mSpeed":12.313880920410156,"mStartTime":0,"mStepCount":1236,"mTimeUnit":600000,"mTotalActiveTime":447522.25784944976,"mWalkStepCount":377},{"mCalorie":15.419999971985817,"mDistance":264.7499969005585,"mNowHealthyStep":0,"mRunStepCount":45,"mSpeed":6.442425727844238,"mStartTime":0,"mStepCount":307,"mTimeUnit":600000,"mTotalActiveTime":147941.16349227302,"mWalkStepCount":262},{"mCalorie":2.950000047683716,"mDistance":54.20999813079834,"mNowHealthyStep":0,"mRunStepCount":0,"mSpeed":4.623584270477295,"mStartTime":0,"mStepCount":71,"mTimeUnit":600000,"mTotalActiveTime":42208.812350970984,"mWalkStepCount":71},{"mCalorie":2.769999921321869,"mDistance":50.09999990463257,"mNowHealthyStep":0,"mRunStepCount":0,"mSpeed":4.641845703125,"mStartTime":0,"mStepCount":66,"mTimeUnit":600000,"mTotalActiveTime":38855.23199267683,"mWalkStepCount":66},{"mCalorie":2.2299999594688416,"mDistance":40.07999801635742,"mNowHealthyStep":0,"mRunStepCount":0,"mSpeed":4.193406105041504,"mStartTime":0,"mStepCount":54,"mTimeUnit":600000,"mTotalActiveTime":34408.30261730499,"mWalkStepCount":54},{"mCalorie":3.3700000047683716,"mDistance":61.58000183105469,"mNowHealthyStep":0,"mRunStepCount":0,"mSpeed":4.398761749267578,"mStartTime":0,"mStepCount":82,"mTimeUnit":600000,"mTotalActiveTime":50397.81834049573,"mWalkStepCount":82},{"mCalorie":2.300000011920929,"mDistance":42.690001010894775,"mNowHealthyStep":0,"mRunStepCount":0,"mSpeed":4.650699138641357,"mStartTime":0,"mStepCount":56,"mTimeUnit":600000,"mTotalActiveTime":33045.356439150535,"mWalkStepCount":56},{"mCalorie":6.399999916553497,"mDistance":123.8400011062622,"mNowHealthyStep":0,"mRunStepCount":0,"mSpeed":5.4212541580200195,"mStartTime":0,"mStepCount":158,"mTimeUnit":600000,"mTotalActiveTime":82236.31878197391,"mWalkStepCount":158},{"mCalorie":0.0,"mDistance":0.0,"mNowHealthyStep":0,"mRunStepCount":0,"mSpeed":0.0,"mStartTime":0,"mStepCount":0,"mTimeUnit":600000,"mTotalActiveTime":0.0,"mWalkStepCount":0},{"mCalorie":14.099996089935303,"mDistance":266.5899772644043,"mNowHealthyStep":0,"mRunStepCount":0,"mSpeed":4.728971481323242,"mStartTime":0,"mStepCount":351,"mTimeUnit":600000,"mTotalActiveTime":202945.58610705362,"mWalkStepCount":351},{"mCalorie":44.799997329711914,"mDistance":867.1100387573242,"mNowHealthyStep":0,"mRunStepCount":0,"mSpeed":5.202660083770752,"mStartTime":0,"mStepCount":1120,"mTimeUnit":600000,"mTotalActiveTime":600000.0014416171,"mWalkStepCount":1120},{"mCalorie":20.19000020623207,"mDistance":388.13000297546387,"mNowHealthyStep":0,"mRunStepCount":0,"mSpeed":5.115285873413086,"mStartTime":0,"mStepCount":502,"mTimeUnit":600000,"mTotalActiveTime":273155.41013317846,"mWalkStepCount":502},{"mCalorie":0.0,"mDistance":0.0,"mNowHealthyStep":0,"mRunStepCount":0,"mSpeed":0.0,"mStartTime":0,"mStepCount":0,"mTimeUnit":600000,"mTotalActiveTime":0.0,"mWalkStepCount":0},{"mCalorie":0.0,"mDistance":0.0,"mNowHealthyStep":0,"mRunStepCount":0,"mSpeed":0.0,"mStartTime":0,"mStepCount":0,"mTimeUnit":600000,"mTotalActiveTime":0.0,"mWalkStepCount":0},{"mCalorie":0.0,"mDistance":0.0,"mNowHealthyStep":0,"mRunStepCount":0,"mSpeed":0.0,"mStartTime":0,"mStepCount":0,"mTimeUnit":600000,"mTotalActiveTime":0.0,"mWalkStepCount":0},{"mCalorie":0.0,"mDistance":0.0,"mNowHealthyStep":0,"mRunStepCount":0,"mSpeed":0.0,"mStartTime":0,"mStepCount":0,"mTimeUnit":600000,"mTotalActiveTime":0.0,"mWalkStepCount":0},{"mCalorie":0.0,"mDistance":0.0,"mNowHealthyStep":0,"mRunStepCount":0,"mSpeed":0.0,"mStartTime":0,"mStepCount":0,"mTimeUnit":600000,"mTotalActiveTime":0.0,"mWalkStepCount":0},{"mCalorie":0.0,"mDistance":0.0,"mNowHealthyStep":0,"mRunStepCount":0,"mSpeed":0.0,"mStartTime":0,"mStepCount":0,"mTimeUnit":600000,"mTotalActiveTime":0.0,"mWalkStepCount":0},{"mCalorie":0.0,"mDistance":0.0,"mNowHealthyStep":0,"mRunStepCount":0,"mSpeed":0.0,"mStartTime":0,"mStepCount":0,"mTimeUnit":600000,"mTotalActiveTime":0.0,"mWalkStepCount":0},{"mCalorie":0.0,"mDistance":0.0,"mNowHealthyStep":0,"mRunStepCount":0,"mSpeed":0.0,"mStartTime":0,"mStepCount":0,"mTimeUnit":600000,"mTotalActiveTime":0.0,"mWalkStepCount":0},{"mCalorie":0.0,"mDistance":0.0,"mNowHealthyStep":0,"mRunStepCount":0,"mSpeed":0.0,"mStartTime":0,"mStepCount":0,"mTimeUnit":600000,"mTotalActiveTime":0.0,"mWalkStepCount":0},{"mCalorie":0.0,"mDistance":0.0,"mNowHealthyStep":0,"mRunStepCount":0,"mSpeed":0.0,"mStartTime":0,"mStepCount":0,"mTimeUnit":600000,"mTotalActiveTime":0.0,"mWalkStepCount":0},{"mCalorie":3.7999999821186066,"mDistance":70.090003490448,"mNowHealthyStep":0,"mRunStepCount":0,"mSpeed":4.72389554977417,"mStartTime":0,"mStepCount":92,"mTimeUnit":600000,"mTotalActiveTime":53414.39179473219,"mWalkStepCount":92},{"mCalorie":4.1600000858306885,"mDistance":79.03000116348267,"mNowHealthyStep":0,"mRunStepCount":0,"mSpeed":5.326939105987549,"mStartTime":0,"mStepCount":100,"mTimeUnit":600000,"mTotalActiveTime":53409.284147358296,"mWalkStepCount":100},{"mCalorie":0.0,"mDistance":0.0,"mNowHealthyStep":0,"mRunStepCount":0,"mSpeed":0.0,"mStartTime":0,"mStepCount":0,"mTimeUnit":600000,"mTotalActiveTime":0.0,"mWalkStepCount":0},{"mCalorie":15.819999694824219,"mDistance":300.11998748779297,"mNowHealthyStep":0,"mRunStepCount":0,"mSpeed":4.6641106605529785,"mStartTime":0,"mStepCount":395,"mTimeUnit":600000,"mTotalActiveTime":231647.99973110665,"mWalkStepCount":395},{"mCalorie":19.889999985694885,"mDistance":357.3799982070923,"mNowHealthyStep":0,"mRunStepCount":0,"mSpeed":3.764827251434326,"mStartTime":0,"mStepCount":488,"mTimeUnit":600000,"mTotalActiveTime":341733.60167063656,"mWalkStepCount":488},{"mCalorie":34.450000047683716,"mDistance":632.5100021362305,"mNowHealthyStep":0,"mRunStepCount":0,"mSpeed":4.098590850830078,"mStartTime":0,"mStepCount":855,"mTimeUnit":600000,"mTotalActiveTime":555565.5863691283,"mWalkStepCount":855},{"mCalorie":3.479999989271164,"mDistance":60.44999885559082,"mNowHealthyStep":0,"mRunStepCount":0,"mSpeed":4.228180408477783,"mStartTime":0,"mStepCount":79,"mTimeUnit":600000,"mTotalActiveTime":51468.94799160297,"mWalkStepCount":79},{"mCalorie":1.9300000071525574,"mDistance":36.88999938964844,"mNowHealthyStep":0,"mRunStepCount":0,"mSpeed":5.669753074645996,"mStartTime":0,"mStepCount":46,"mTimeUnit":600000,"mTotalActiveTime":23423.24176872864,"mWalkStepCount":46},{"mCalorie":11.749998420476913,"mDistance":219.77004623413086,"mNowHealthyStep":0,"mRunStepCount":0,"mSpeed":4.4076151847839355,"mStartTime":0,"mStepCount":292,"mTimeUnit":600000,"mTotalActiveTime":179501.1852898335,"mWalkStepCount":292},{"mCalorie":25.699999809265137,"mDistance":480.26999282836914,"mNowHealthyStep":0,"mRunStepCount":0,"mSpeed":4.434897422790527,"mStartTime":0,"mStepCount":638,"mTimeUnit":600000,"mTotalActiveTime":389856.1309083192,"mWalkStepCount":638},{"mCalorie":27.98999983072281,"mDistance":522.709997177124,"mNowHealthyStep":0,"mRunStepCount":0,"mSpeed":4.493639945983887,"mStartTime":0,"mStepCount":695,"mTimeUnit":600000,"mTotalActiveTime":418759.8514162604,"mWalkStepCount":695},{"mCalorie":12.25,"mDistance":225.31000137329102,"mNowHealthyStep":0,"mRunStepCount":0,"mSpeed":4.155069828033447,"mStartTime":0,"mStepCount":302,"mTimeUnit":600000,"mTotalActiveTime":195211.16932749568,"mWalkStepCount":302}]