[{"elapsed_time":170459,"segment":1,"source_type":4,"start_time":1653898112908},{"elapsed_time":180459,"segment":1,"source_type":4,"start_time":1653898122908},{"elapsed_time":190459,"segment":1,"source_type":4,"start_time":1653898132908},{"elapsed_time":200459,"segment":1,"source_type":4,"start_time":1653898142908},{"elapsed_time":240459,"segment":1,"source_type":4,"start_time":1653898182908},{"elapsed_time":300459,"segment":1,"source_type":4,"start_time":1653898242908},{"elapsed_time":360459,"segment":1,"source_type":4,"start_time":1653898302908},{"elapsed_time":420459,"segment":1,"source_type":4,"start_time":1653898362908},{"elapsed_time":480466,"segment":1,"source_type":4,"start_time":1653898422915},{"elapsed_time":540618,"segment":1,"source_type":4,"start_time":1653898483067},{"elapsed_time":547618,"segment":1,"source_type":4,"start_time":1653898490067},{"elapsed_time":550618,"segment":1,"source_type":4,"start_time":1653898493067},{"elapsed_time":600697,"segment":1,"source_type":4,"start_time":1653898543146},{"elapsed_time":660652,"segment":1,"source_type":4,"start_time":1653898603101},{"elapsed_time":720652,"segment":1,"source_type":4,"start_time":1653898663101},{"elapsed_time":780652,"segment":1,"source_type":4,"start_time":1653898723101},{"elapsed_time":840464,"segment":1,"source_type":4,"start_time":1653898782913},{"elapsed_time":900464,"segment":1,"source_type":4,"start_time":1653898842913},{"elapsed_time":960649,"segment":1,"source_type":4,"start_time":1653898903098},{"elapsed_time":1020959,"segment":1,"source_type":4,"start_time":1653898963408},{"elapsed_time":1080959,"segment":1,"source_type":4,"start_time":1653899023408},{"elapsed_time":1140959,"segment":1,"source_type":4,"start_time":1653899083408},{"elapsed_time":1200959,"segment":1,"source_type":4,"start_time":1653899143408},{"elapsed_time":1000,"segment":1,"source_type":4,"start_time":1653897943449},{"elapsed_time":60000,"segment":1,"source_type":4,"start_time":1653898002449},{"elapsed_time":120000,"segment":1,"source_type":4,"start_time":1653898062449},{"elapsed_time":180000,"segment":1,"source_type":4,"start_time":1653898122449},{"elapsed_time":240000,"segment":1,"source_type":4,"start_time":1653898182449},{"elapsed_time":300000,"segment":1,"source_type":4,"start_time":1653898242449},{"elapsed_time":360000,"segment":1,"source_type":4,"start_time":1653898302449},{"elapsed_time":420000,"segment":1,"source_type":4,"start_time":1653898362449},{"elapsed_time":480000,"segment":1,"source_type":4,"start_time":1653898422449},{"elapsed_time":480000,"segment":1,"source_type":4,"start_time":1653898422449},{"elapsed_time":540000,"segment":1,"source_type":4,"start_time":1653898482449},{"elapsed_time":600000,"segment":1,"source_type":4,"start_time":1653898542449},{"elapsed_time":660000,"segment":1,"source_type":4,"start_time":1653898602449},{"elapsed_time":720000,"segment":1,"source_type":4,"start_time":1653898662449},{"elapsed_time":780000,"segment":1,"source_type":4,"start_time":1653898722449},{"elapsed_time":840000,"segment":1,"source_type":4,"start_time":1653898782449},{"elapsed_time":840000,"segment":1,"source_type":4,"start_time":1653898782449},{"elapsed_time":900000,"segment":1,"source_type":4,"start_time":1653898842449},{"elapsed_time":960000,"segment":1,"source_type":4,"start_time":1653898902449},{"elapsed_time":1020000,"segment":1,"source_type":4,"start_time":1653898962450},{"elapsed_time":1080000,"segment":1,"source_type":4,"start_time":1653899022449},{"elapsed_time":1140000,"segment":1,"source_type":4,"start_time":1653899082449},{"elapsed_time":1200000,"segment":1,"source_type":4,"start_time":1653899142449},{"elapsed_time":1200000,"segment":1,"source_type":4,"start_time":1653899142449}]