[{"mCalorie":0.0,"mDistance":0.0,"mNowHealthyStep":0,"mRunStepCount":0,"mSpeed":0.0,"mStartTime":1655848800000,"mStepCount":0,"mTimeUnit":600000,"mTotalActiveTime":0.0,"mWalkStepCount":0},{"mCalorie":0.0,"mDistance":0.0,"mNowHealthyStep":0,"mRunStepCount":0,"mSpeed":0.0,"mStartTime":1655849400000,"mStepCount":0,"mTimeUnit":600000,"mTotalActiveTime":0.0,"mWalkStepCount":0},{"mCalorie":0.0,"mDistance":0.0,"mNowHealthyStep":0,"mRunStepCount":0,"mSpeed":0.0,"mStartTime":1655850000000,"mStepCount":0,"mTimeUnit":600000,"mTotalActiveTime":0.0,"mWalkStepCount":0},{"mCalorie":0.0,"mDistance":0.0,"mNowHealthyStep":0,"mRunStepCount":0,"mSpeed":0.0,"mStartTime":1655850600000,"mStepCount":0,"mTimeUnit":600000,"mTotalActiveTime":0.0,"mWalkStepCount":0},{"mCalorie":0.0,"mDistance":0.0,"mNowHealthyStep":0,"mRunStepCount":0,"mSpeed":0.0,"mStartTime":1655851200000,"mStepCount":0,"mTimeUnit":600000,"mTotalActiveTime":0.0,"mWalkStepCount":0},{"mCalorie":0.0,"mDistance":0.0,"mNowHealthyStep":0,"mRunStepCount":0,"mSpeed":0.0,"mStartTime":1655851800000,"mStepCount":0,"mTimeUnit":600000,"mTotalActiveTime":0.0,"mWalkStepCount":0},{"mCalorie":0.0,"mDistance":0.0,"mNowHealthyStep":0,"mRunStepCount":0,"mSpeed":0.0,"mStartTime":1655852400000,"mStepCount":0,"mTimeUnit":600000,"mTotalActiveTime":0.0,"mWalkStepCount":0},{"mCalorie":0.0,"mDistance":0.0,"mNowHealthyStep":0,"mRunStepCount":0,"mSpeed":0.0,"mStartTime":1655853000000,"mStepCount":0,"mTimeUnit":600000,"mTotalActiveTime":0.0,"mWalkStepCount":0},{"mCalorie":0.0,"mDistance":0.0,"mNowHealthyStep":0,"mRunStepCount":0,"mSpeed":0.0,"mStartTime":1655853600000,"mStepCount":0,"mTimeUnit":600000,"mTotalActiveTime":0.0,"mWalkStepCount":0},{"mCalorie":0.0,"mDistance":0.0,"mNowHealthyStep":0,"mRunStepCount":0,"mSpeed":0.0,"mStartTime":1655854200000,"mStepCount":0,"mTimeUnit":600000,"mTotalActiveTime":0.0,"mWalkStepCount":0},{"mCalorie":0.0,"mDistance":0.0,"mNowHealthyStep":0,"mRunStepCount":0,"mSpeed":0.0,"mStartTime":1655854800000,"mStepCount":0,"mTimeUnit":600000,"mTotalActiveTime":0.0,"mWalkStepCount":0},{"mCalorie":0.0,"mDistance":0.0,"mNowHealthyStep":0,"mRunStepCount":0,"mSpeed":0.0,"mStartTime":1655855400000,"mStepCount":0,"mTimeUnit":600000,"mTotalActiveTime":0.0,"mWalkStepCount":0},{"mCalorie":0.0,"mDistance":0.0,"mNowHealthyStep":0,"mRunStepCount":0,"mSpeed":0.0,"mStartTime":1655856000000,"mStepCount":0,"mTimeUnit":600000,"mTotalActiveTime":0.0,"mWalkStepCount":0},{"mCalorie":0.0,"mDistance":0.0,"mNowHealthyStep":0,"mRunStepCount":0,"mSpeed":0.0,"mStartTime":1655856600000,"mStepCount":0,"mTimeUnit":600000,"mTotalActiveTime":0.0,"mWalkStepCount":0},{"mCalorie":0.0,"mDistance":0.0,"mNowHealthyStep":0,"mRunStepCount":0,"mSpeed":0.0,"mStartTime":1655857200000,"mStepCount":0,"mTimeUnit":600000,"mTotalActiveTime":0.0,"mWalkStepCount":0},{"mCalorie":0.0,"mDistance":0.0,"mNowHealthyStep":0,"mRunStepCount":0,"mSpeed":0.0,"mStartTime":1655857800000,"mStepCount":0,"mTimeUnit":600000,"mTotalActiveTime":0.0,"mWalkStepCount":0},{"mCalorie":0.0,"mDistance":0.0,"mNowHealthyStep":0,"mRunStepCount":0,"mSpeed":0.0,"mStartTime":1655858400000,"mStepCount":0,"mTimeUnit":600000,"mTotalActiveTime":0.0,"mWalkStepCount":0},{"mCalorie":0.0,"mDistance":0.0,"mNowHealthyStep":0,"mRunStepCount":0,"mSpeed":0.0,"mStartTime":1655859000000,"mStepCount":0,"mTimeUnit":600000,"mTotalActiveTime":0.0,"mWalkStepCount":0},{"mCalorie":0.0,"mDistance":0.0,"mNowHealthyStep":0,"mRunStepCount":0,"mSpeed":0.0,"mStartTime":1655859600000,"mStepCount":0,"mTimeUnit":600000,"mTotalActiveTime":0.0,"mWalkStepCount":0},{"mCalorie":0.0,"mDistance":0.0,"mNowHealthyStep":0,"mRunStepCount":0,"mSpeed":0.0,"mStartTime":1655860200000,"mStepCount":0,"mTimeUnit":600000,"mTotalActiveTime":0.0,"mWalkStepCount":0},{"mCalorie":0.0,"mDistance":0.0,"mNowHealthyStep":0,"mRunStepCount":0,"mSpeed":0.0,"mStartTime":1655860800000,"mStepCount":0,"mTimeUnit":600000,"mTotalActiveTime":0.0,"mWalkStepCount":0},{"mCalorie":0.0,"mDistance":0.0,"mNowHealthyStep":0,"mRunStepCount":0,"mSpeed":0.0,"mStartTime":1655861400000,"mStepCount":0,"mTimeUnit":600000,"mTotalActiveTime":0.0,"mWalkStepCount":0},{"mCalorie":0.0,"mDistance":0.0,"mNowHealthyStep":0,"mRunStepCount":0,"mSpeed":0.0,"mStartTime":1655862000000,"mStepCount":0,"mTimeUnit":600000,"mTotalActiveTime":0.0,"mWalkStepCount":0},{"mCalorie":0.0,"mDistance":0.0,"mNowHealthyStep":0,"mRunStepCount":0,"mSpeed":0.0,"mStartTime":1655862600000,"mStepCount":0,"mTimeUnit":600000,"mTotalActiveTime":0.0,"mWalkStepCount":0},{"mCalorie":0.0,"mDistance":0.0,"mNowHealthyStep":0,"mRunStepCount":0,"mSpeed":0.0,"mStartTime":1655863200000,"mStepCount":0,"mTimeUnit":600000,"mTotalActiveTime":0.0,"mWalkStepCount":0},{"mCalorie":0.0,"mDistance":0.0,"mNowHealthyStep":0,"mRunStepCount":0,"mSpeed":0.0,"mStartTime":1655863800000,"mStepCount":0,"mTimeUnit":600000,"mTotalActiveTime":0.0,"mWalkStepCount":0},{"mCalorie":0.0,"mDistance":0.0,"mNowHealthyStep":0,"mRunStepCount":0,"mSpeed":0.0,"mStartTime":1655864400000,"mStepCount":0,"mTimeUnit":600000,"mTotalActiveTime":0.0,"mWalkStepCount":0},{"mCalorie":0.0,"mDistance":0.0,"mNowHealthyStep":0,"mRunStepCount":0,"mSpeed":0.0,"mStartTime":1655865000000,"mStepCount":0,"mTimeUnit":600000,"mTotalActiveTime":0.0,"mWalkStepCount":0},{"mCalorie":0.0,"mDistance":0.0,"mNowHealthyStep":0,"mRunStepCount":0,"mSpeed":0.0,"mStartTime":1655865600000,"mStepCount":0,"mTimeUnit":600000,"mTotalActiveTime":0.0,"mWalkStepCount":0},{"mCalorie":0.0,"mDistance":0.0,"mNowHealthyStep":0,"mRunStepCount":0,"mSpeed":0.0,"mStartTime":1655866200000,"mStepCount":0,"mTimeUnit":600000,"mTotalActiveTime":0.0,"mWalkStepCount":0},{"mCalorie":0.0,"mDistance":0.0,"mNowHealthyStep":0,"mRunStepCount":0,"mSpeed":0.0,"mStartTime":1655866800000,"mStepCount":0,"mTimeUnit":600000,"mTotalActiveTime":0.0,"mWalkStepCount":0},{"mCalorie":0.0,"mDistance":0.0,"mNowHealthyStep":0,"mRunStepCount":0,"mSpeed":0.0,"mStartTime":1655867400000,"mStepCount":0,"mTimeUnit":600000,"mTotalActiveTime":0.0,"mWalkStepCount":0},{"mCalorie":0.0,"mDistance":0.0,"mNowHealthyStep":0,"mRunStepCount":0,"mSpeed":0.0,"mStartTime":1655868000000,"mStepCount":0,"mTimeUnit":600000,"mTotalActiveTime":0.0,"mWalkStepCount":0},{"mCalorie":0.0,"mDistance":0.0,"mNowHealthyStep":0,"mRunStepCount":0,"mSpeed":0.0,"mStartTime":1655868600000,"mStepCount":0,"mTimeUnit":600000,"mTotalActiveTime":0.0,"mWalkStepCount":0},{"mCalorie":0.0,"mDistance":0.0,"mNowHealthyStep":0,"mRunStepCount":0,"mSpeed":0.0,"mStartTime":1655869200000,"mStepCount":0,"mTimeUnit":600000,"mTotalActiveTime":0.0,"mWalkStepCount":0},{"mCalorie":0.0,"mDistance":0.0,"mNowHealthyStep":0,"mRunStepCount":0,"mSpeed":0.0,"mStartTime":1655869800000,"mStepCount":0,"mTimeUnit":600000,"mTotalActiveTime":0.0,"mWalkStepCount":0},{"mCalorie":0.0,"mDistance":0.0,"mNowHealthyStep":0,"mRunStepCount":0,"mSpeed":0.0,"mStartTime":1655870400000,"mStepCount":0,"mTimeUnit":600000,"mTotalActiveTime":0.0,"mWalkStepCount":0},{"mCalorie":0.0,"mDistance":0.0,"mNowHealthyStep":0,"mRunStepCount":0,"mSpeed":0.0,"mStartTime":1655871000000,"mStepCount":0,"mTimeUnit":600000,"mTotalActiveTime":0.0,"mWalkStepCount":0},{"mCalorie":0.0,"mDistance":0.0,"mNowHealthyStep":0,"mRunStepCount":0,"mSpeed":0.0,"mStartTime":1655871600000,"mStepCount":0,"mTimeUnit":600000,"mTotalActiveTime":0.0,"mWalkStepCount":0},{"mCalorie":0.0,"mDistance":0.0,"mNowHealthyStep":0,"mRunStepCount":0,"mSpeed":0.0,"mStartTime":1655872200000,"mStepCount":0,"mTimeUnit":600000,"mTotalActiveTime":0.0,"mWalkStepCount":0},{"mCalorie":0.0,"mDistance":0.0,"mNowHealthyStep":0,"mRunStepCount":0,"mSpeed":0.0,"mStartTime":1655872800000,"mStepCount":0,"mTimeUnit":600000,"mTotalActiveTime":0.0,"mWalkStepCount":0},{"mCalorie":0.0,"mDistance":0.0,"mNowHealthyStep":0,"mRunStepCount":0,"mSpeed":0.0,"mStartTime":1655873400000,"mStepCount":0,"mTimeUnit":600000,"mTotalActiveTime":0.0,"mWalkStepCount":0},{"mCalorie":0.23999999463558197,"mDistance":4.820000171661377,"mNowHealthyStep":0,"mRunStepCount":0,"mSpeed":6.900000095367432,"mStartTime":1655874000000,"mStepCount":6,"mTimeUnit":600000,"mTotalActiveTime":2514.7826635003757,"mWalkStepCount":6},{"mCalorie":0.6299999952316284,"mDistance":11.0,"mNowHealthyStep":0,"mRunStepCount":0,"mSpeed":3.9306042194366455,"mStartTime":1655874600000,"mStepCount":15,"mTimeUnit":600000,"mTotalActiveTime":10074.78692567925,"mWalkStepCount":15},{"mCalorie":0.0,"mDistance":0.0,"mNowHealthyStep":0,"mRunStepCount":0,"mSpeed":0.0,"mStartTime":1655875200000,"mStepCount":0,"mTimeUnit":600000,"mTotalActiveTime":0.0,"mWalkStepCount":0},{"mCalorie":1.7200000286102295,"mDistance":31.799999713897705,"mNowHealthyStep":0,"mRunStepCount":0,"mSpeed":4.7412800788879395,"mStartTime":1655875800000,"mStepCount":42,"mTimeUnit":600000,"mTotalActiveTime":24145.37897171221,"mWalkStepCount":42},{"mCalorie":1.409999966621399,"mDistance":23.970001220703125,"mNowHealthyStep":0,"mRunStepCount":0,"mSpeed":3.631855010986328,"mStartTime":1655876400000,"mStepCount":33,"mTimeUnit":600000,"mTotalActiveTime":23759.760344914743,"mWalkStepCount":33},{"mCalorie":0.6100000143051147,"mDistance":11.179999351501465,"mNowHealthyStep":0,"mRunStepCount":0,"mSpeed":4.251270771026611,"mStartTime":1655877000000,"mStepCount":15,"mTimeUnit":600000,"mTotalActiveTime":9467.286332290252,"mWalkStepCount":15},{"mCalorie":5.399999916553497,"mDistance":98.63000011444092,"mNowHealthyStep":0,"mRunStepCount":0,"mSpeed":4.178852081298828,"mStartTime":1655877600000,"mStepCount":132,"mTimeUnit":600000,"mTotalActiveTime":84967.83096411916,"mWalkStepCount":132},{"mCalorie":0.0,"mDistance":0.0,"mNowHealthyStep":0,"mRunStepCount":0,"mSpeed":0.0,"mStartTime":1655878200000,"mStepCount":0,"mTimeUnit":600000,"mTotalActiveTime":0.0,"mWalkStepCount":0},{"mCalorie":8.900000035762787,"mDistance":152.7899990081787,"mNowHealthyStep":0,"mRunStepCount":0,"mSpeed":3.8163461685180664,"mStartTime":1655878800000,"mStepCount":231,"mTimeUnit":600000,"mTotalActiveTime":144128.43826792948,"mWalkStepCount":231},{"mCalorie":12.029999986290932,"mDistance":218.00000071525574,"mNowHealthyStep":0,"mRunStepCount":0,"mSpeed":4.458548069000244,"mStartTime":1655879400000,"mStepCount":308,"mTimeUnit":600000,"mTotalActiveTime":176021.43656013175,"mWalkStepCount":308},{"mCalorie":12.519999921321869,"mDistance":227.8900055885315,"mNowHealthyStep":0,"mRunStepCount":0,"mSpeed":4.517246246337891,"mStartTime":1655880000000,"mStepCount":336,"mTimeUnit":600000,"mTotalActiveTime":181615.96830955893,"mWalkStepCount":336},{"mCalorie":9.700234472751617,"mDistance":175.85562229156494,"mNowHealthyStep":0,"mRunStepCount":0,"mSpeed":4.554902076721191,"mStartTime":1655880600000,"mStepCount":253,"mTimeUnit":600000,"mTotalActiveTime":138988.77071996537,"mWalkStepCount":253},{"mCalorie":17.63984376192093,"mDistance":317.73875427246094,"mNowHealthyStep":0,"mRunStepCount":0,"mSpeed":4.516574382781982,"mStartTime":1655881200000,"mStepCount":483,"mTimeUnit":600000,"mTotalActiveTime":253258.20146984246,"mWalkStepCount":483},{"mCalorie":13.399746149778366,"mDistance":241.84499979019165,"mNowHealthyStep":0,"mRunStepCount":0,"mSpeed":4.394290447235107,"mStartTime":1655881800000,"mStepCount":347,"mTimeUnit":600000,"mTotalActiveTime":198130.2805756792,"mWalkStepCount":347},{"mCalorie":15.369999885559082,"mDistance":293.83000087738037,"mNowHealthyStep":0,"mRunStepCount":0,"mSpeed":4.982668876647949,"mStartTime":1655882400000,"mStepCount":389,"mTimeUnit":600000,"mTotalActiveTime":212293.46414077195,"mWalkStepCount":389},{"mCalorie":3.180000066757202,"mDistance":53.75,"mNowHealthyStep":0,"mRunStepCount":0,"mSpeed":3.836315393447876,"mStartTime":1655883000000,"mStepCount":88,"mTimeUnit":600000,"mTotalActiveTime":50439.02393427963,"mWalkStepCount":88},{"mCalorie":7.129511713981628,"mDistance":119.49031209945679,"mNowHealthyStep":0,"mRunStepCount":0,"mSpeed":3.6018266677856445,"mStartTime":1655883600000,"mStepCount":195,"mTimeUnit":600000,"mTotalActiveTime":119429.71163759835,"mWalkStepCount":195},{"mCalorie":1.210058569908142,"mDistance":19.95343780517578,"mNowHealthyStep":0,"mRunStepCount":0,"mSpeed":3.1370856761932373,"mStartTime":1655884200000,"mStepCount":32,"mTimeUnit":600000,"mTotalActiveTime":22897.80500537662,"mWalkStepCount":32},{"mCalorie":0.0,"mDistance":0.0,"mNowHealthyStep":0,"mRunStepCount":0,"mSpeed":0.0,"mStartTime":1655884800000,"mStepCount":0,"mTimeUnit":600000,"mTotalActiveTime":0.0,"mWalkStepCount":0},{"mCalorie":9.349707007408142,"mDistance":170.3890619277954,"mNowHealthyStep":0,"mRunStepCount":0,"mSpeed":4.388566493988037,"mStartTime":1655885400000,"mStepCount":263,"mTimeUnit":600000,"mTotalActiveTime":139772.4336266247,"mWalkStepCount":263},{"mCalorie":7.999765545129776,"mDistance":141.26343488693237,"mNowHealthyStep":0,"mRunStepCount":0,"mSpeed":4.249721050262451,"mStartTime":1655886000000,"mStepCount":217,"mTimeUnit":600000,"mTotalActiveTime":119666.28734318248,"mWalkStepCount":217},{"mCalorie":12.709998846054077,"mDistance":229.09000396728516,"mNowHealthyStep":0,"mRunStepCount":0,"mSpeed":4.450199604034424,"mStartTime":1655886600000,"mStepCount":332,"mTimeUnit":600000,"mTotalActiveTime":185322.93521686224,"mWalkStepCount":332},{"mCalorie":8.689998626708984,"mDistance":164.12998962402344,"mNowHealthyStep":0,"mRunStepCount":0,"mSpeed":4.8162007331848145,"mStartTime":1655887200000,"mStepCount":224,"mTimeUnit":600000,"mTotalActiveTime":122683.41442493165,"mWalkStepCount":224},{"mCalorie":13.079998046159744,"mDistance":236.8599991798401,"mNowHealthyStep":0,"mRunStepCount":0,"mSpeed":4.358474254608154,"mStartTime":1655887800000,"mStepCount":355,"mTimeUnit":600000,"mTotalActiveTime":195640.9469565286,"mWalkStepCount":355},{"mCalorie":12.760117053985596,"mDistance":234.75094509124756,"mNowHealthyStep":0,"mRunStepCount":0,"mSpeed":4.717593193054199,"mStartTime":1655888400000,"mStepCount":330,"mTimeUnit":600000,"mTotalActiveTime":179138.6770151832,"mWalkStepCount":330},{"mCalorie":8.310000032186508,"mDistance":159.64000129699707,"mNowHealthyStep":0,"mRunStepCount":0,"mSpeed":5.141632556915283,"mStartTime":1655889000000,"mStepCount":207,"mTimeUnit":600000,"mTotalActiveTime":111774.6123056085,"mWalkStepCount":207},{"mCalorie":8.050038695335388,"mDistance":139.51937866210938,"mNowHealthyStep":0,"mRunStepCount":0,"mSpeed":4.1811041831970215,"mStartTime":1655889600000,"mStepCount":211,"mTimeUnit":600000,"mTotalActiveTime":120128.49329749621,"mWalkStepCount":211},{"mCalorie":13.879218757152557,"mDistance":249.29562950134277,"mNowHealthyStep":0,"mRunStepCount":0,"mSpeed":4.320095062255859,"mStartTime":1655890200000,"mStepCount":381,"mTimeUnit":600000,"mTotalActiveTime":207741.786046688,"mWalkStepCount":381},{"mCalorie":7.019999772310257,"mDistance":131.0,"mNowHealthyStep":0,"mRunStepCount":0,"mSpeed":4.422804832458496,"mStartTime":1655890800000,"mStepCount":187,"mTimeUnit":600000,"mTotalActiveTime":106629.1710482853,"mWalkStepCount":187},{"mCalorie":2.0999999940395355,"mDistance":40.22000026702881,"mNowHealthyStep":0,"mRunStepCount":0,"mSpeed":4.696058750152588,"mStartTime":1655891400000,"mStepCount":55,"mTimeUnit":600000,"mTotalActiveTime":30832.6629294328,"mWalkStepCount":55},{"mCalorie":9.53021490573883,"mDistance":171.1862554550171,"mNowHealthyStep":0,"mRunStepCount":0,"mSpeed":4.5347580909729,"mStartTime":1655892000000,"mStepCount":254,"mTimeUnit":600000,"mTotalActiveTime":135899.32235042483,"mWalkStepCount":254},{"mCalorie":15.319570302963257,"mDistance":262.4956226348877,"mNowHealthyStep":0,"mRunStepCount":31,"mSpeed":5.2445597648620605,"mStartTime":1655892600000,"mStepCount":372,"mTimeUnit":600000,"mTotalActiveTime":180183.7136596823,"mWalkStepCount":341},{"mCalorie":8.030000030994415,"mDistance":153.5900001525879,"mNowHealthyStep":0,"mRunStepCount":0,"mSpeed":5.2131829261779785,"mStartTime":1655893200000,"mStepCount":201,"mTimeUnit":600000,"mTotalActiveTime":106062.64669745615,"mWalkStepCount":201},{"mCalorie":18.899999618530273,"mDistance":336.9000005722046,"mNowHealthyStep":0,"mRunStepCount":0,"mSpeed":4.215227127075195,"mStartTime":1655893800000,"mStepCount":519,"mTimeUnit":600000,"mTotalActiveTime":287728.27344400337,"mWalkStepCount":519},{"mCalorie":9.109804630279541,"mDistance":165.4331283569336,"mNowHealthyStep":0,"mRunStepCount":0,"mSpeed":4.478431701660156,"mStartTime":1655894400000,"mStepCount":234,"mTimeUnit":600000,"mTotalActiveTime":132983.89137581474,"mWalkStepCount":234},{"mCalorie":18.559824407100677,"mDistance":330.2643756866455,"mNowHealthyStep":0,"mRunStepCount":0,"mSpeed":4.219645977020264,"mStartTime":1655895000000,"mStepCount":495,"mTimeUnit":600000,"mTotalActiveTime":281765.75686086505,"mWalkStepCount":495},{"mCalorie":10.219999939203262,"mDistance":192.66000413894653,"mNowHealthyStep":0,"mRunStepCount":0,"mSpeed":4.882745742797852,"mStartTime":1655895600000,"mStepCount":271,"mTimeUnit":600000,"mTotalActiveTime":142046.30680583342,"mWalkStepCount":271},{"mCalorie":4.550000041723251,"mDistance":84.11000442504883,"mNowHealthyStep":0,"mRunStepCount":0,"mSpeed":4.532403945922852,"mStartTime":1655896200000,"mStepCount":113,"mTimeUnit":600000,"mTotalActiveTime":66806.93345519828,"mWalkStepCount":113},{"mCalorie":0.0,"mDistance":0.0,"mNowHealthyStep":0,"mRunStepCount":0,"mSpeed":0.0,"mStartTime":1655896800000,"mStepCount":0,"mTimeUnit":600000,"mTotalActiveTime":0.0,"mWalkStepCount":0},{"mCalorie":5.309999972581863,"mDistance":95.00999689102173,"mNowHealthyStep":0,"mRunStepCount":0,"mSpeed":4.368867874145508,"mStartTime":1655897400000,"mStepCount":135,"mTimeUnit":600000,"mTotalActiveTime":78289.39013777529,"mWalkStepCount":135},{"mCalorie":6.559999763965607,"mDistance":117.17999410629272,"mNowHealthyStep":0,"mRunStepCount":0,"mSpeed":4.235604286193848,"mStartTime":1655898000000,"mStepCount":167,"mTimeUnit":600000,"mTotalActiveTime":99595.69660954221,"mWalkStepCount":167},{"mCalorie":7.089999973773956,"mDistance":127.69999933242798,"mNowHealthyStep":0,"mRunStepCount":0,"mSpeed":4.057011604309082,"mStartTime":1655898600000,"mStepCount":182,"mTimeUnit":600000,"mTotalActiveTime":113314.92904579204,"mWalkStepCount":182},{"mCalorie":3.6999999061226845,"mDistance":65.66000062227249,"mNowHealthyStep":0,"mRunStepCount":0,"mSpeed":4.010960102081299,"mStartTime":1655899200000,"mStepCount":97,"mTimeUnit":600000,"mTotalActiveTime":58932.520870323904,"mWalkStepCount":97},{"mCalorie":2.0199999809265137,"mDistance":34.6899995803833,"mNowHealthyStep":0,"mRunStepCount":0,"mSpeed":3.7920753955841064,"mStartTime":1655899800000,"mStepCount":56,"mTimeUnit":600000,"mTotalActiveTime":32932.889761192884,"mWalkStepCount":56},{"mCalorie":15.039492070674896,"mDistance":273.6203136444092,"mNowHealthyStep":0,"mRunStepCount":0,"mSpeed":4.489065170288086,"mStartTime":1655900400000,"mStepCount":401,"mTimeUnit":600000,"mTotalActiveTime":219429.4672954356,"mWalkStepCount":401},{"mCalorie":12.29974627494812,"mDistance":212.67656135559082,"mNowHealthyStep":0,"mRunStepCount":0,"mSpeed":4.044722080230713,"mStartTime":1655901000000,"mStepCount":318,"mTimeUnit":600000,"mTotalActiveTime":189292.5265349024,"mWalkStepCount":318},{"mCalorie":9.58964828401804,"mDistance":172.89937591552734,"mNowHealthyStep":0,"mRunStepCount":8,"mSpeed":4.930736541748047,"mStartTime":1655901600000,"mStepCount":238,"mTimeUnit":600000,"mTotalActiveTime":126236.2573772635,"mWalkStepCount":230},{"mCalorie":0.0,"mDistance":0.0,"mNowHealthyStep":0,"mRunStepCount":0,"mSpeed":0.0,"mStartTime":1655902200000,"mStepCount":0,"mTimeUnit":600000,"mTotalActiveTime":0.0,"mWalkStepCount":0},{"mCalorie":8.729998975992203,"mDistance":159.19001483917236,"mNowHealthyStep":0,"mRunStepCount":0,"mSpeed":4.229532241821289,"mStartTime":1655902800000,"mStepCount":225,"mTimeUnit":600000,"mTotalActiveTime":135495.85407031013,"mWalkStepCount":225},{"mCalorie":0.0,"mDistance":0.0,"mNowHealthyStep":0,"mRunStepCount":0,"mSpeed":0.0,"mStartTime":1655903400000,"mStepCount":0,"mTimeUnit":600000,"mTotalActiveTime":0.0,"mWalkStepCount":0},{"mCalorie":0.9499999582767487,"mDistance":17.87000036239624,"mNowHealthyStep":0,"mRunStepCount":0,"mSpeed":5.226083755493164,"mStartTime":1655904000000,"mStepCount":23,"mTimeUnit":600000,"mTotalActiveTime":12309.791216963324,"mWalkStepCount":23},{"mCalorie":0.28999999165534973,"mDistance":5.25,"mNowHealthyStep":0,"mRunStepCount":0,"mSpeed":4.438957691192627,"mStartTime":1655904600000,"mStepCount":7,"mTimeUnit":600000,"mTotalActiveTime":4257.756283079617,"mWalkStepCount":7},{"mCalorie":0.0,"mDistance":0.0,"mNowHealthyStep":0,"mRunStepCount":0,"mSpeed":0.0,"mStartTime":1655905200000,"mStepCount":0,"mTimeUnit":600000,"mTotalActiveTime":0.0,"mWalkStepCount":0},{"mCalorie":0.0,"mDistance":0.0,"mNowHealthyStep":0,"mRunStepCount":0,"mSpeed":0.0,"mStartTime":1655905800000,"mStepCount":0,"mTimeUnit":600000,"mTotalActiveTime":0.0,"mWalkStepCount":0},{"mCalorie":0.0,"mDistance":0.0,"mNowHealthyStep":0,"mRunStepCount":0,"mSpeed":0.0,"mStartTime":1655906400000,"mStepCount":0,"mTimeUnit":600000,"mTotalActiveTime":0.0,"mWalkStepCount":0},{"mCalorie":0.4599999785423279,"mDistance":8.160000801086426,"mNowHealthyStep":0,"mRunStepCount":0,"mSpeed":4.003167629241943,"mStartTime":1655907000000,"mStepCount":11,"mTimeUnit":600000,"mTotalActiveTime":7338.189555023429,"mWalkStepCount":11},{"mCalorie":0.0,"mDistance":0.0,"mNowHealthyStep":0,"mRunStepCount":0,"mSpeed":0.0,"mStartTime":1655907600000,"mStepCount":0,"mTimeUnit":600000,"mTotalActiveTime":0.0,"mWalkStepCount":0},{"mCalorie":0.0,"mDistance":0.0,"mNowHealthyStep":0,"mRunStepCount":0,"mSpeed":0.0,"mStartTime":1655908200000,"mStepCount":0,"mTimeUnit":600000,"mTotalActiveTime":0.0,"mWalkStepCount":0},{"mCalorie":0.0,"mDistance":0.0,"mNowHealthyStep":0,"mRunStepCount":0,"mSpeed":0.0,"mStartTime":1655908800000,"mStepCount":0,"mTimeUnit":600000,"mTotalActiveTime":0.0,"mWalkStepCount":0},{"mCalorie":3.7499998807907104,"mDistance":67.78000020980835,"mNowHealthyStep":0,"mRunStepCount":0,"mSpeed":4.214644432067871,"mStartTime":1655909400000,"mStepCount":91,"mTimeUnit":600000,"mTotalActiveTime":57895.278136149056,"mWalkStepCount":91},{"mCalorie":6.639999836683273,"mDistance":112.24999952316284,"mNowHealthyStep":0,"mRunStepCount":0,"mSpeed":3.819493532180786,"mStartTime":1655910000000,"mStepCount":182,"mTimeUnit":600000,"mTotalActiveTime":105799.36465004191,"mWalkStepCount":182},{"mCalorie":11.23009768128395,"mDistance":197.07312774658203,"mNowHealthyStep":0,"mRunStepCount":0,"mSpeed":4.419783115386963,"mStartTime":1655910600000,"mStepCount":290,"mTimeUnit":600000,"mTotalActiveTime":160519.93038005012,"mWalkStepCount":290},{"mCalorie":44.66999077796936,"mDistance":867.8597640991211,"mNowHealthyStep":0,"mRunStepCount":0,"mSpeed":5.352136611938477,"mStartTime":1655911200000,"mStepCount":1131,"mTimeUnit":600000,"mTotalActiveTime":583747.2641855597,"mWalkStepCount":1131},{"mCalorie":26.8899584710598,"mDistance":499.86528968811035,"mNowHealthyStep":0,"mRunStepCount":0,"mSpeed":4.786999225616455,"mStartTime":1655911800000,"mStepCount":692,"mTimeUnit":600000,"mTotalActiveTime":375917.143598301,"mWalkStepCount":692},{"mCalorie":139.15000104904175,"mDistance":1871.1399765014648,"mNowHealthyStep":0,"mRunStepCount":1107,"mSpeed":12.442286491394043,"mStartTime":1655912400000,"mStepCount":1548,"mTimeUnit":600000,"mTotalActiveTime":541387.9421545039,"mWalkStepCount":441},{"mCalorie":14.620000004768372,"mDistance":282.7899980545044,"mNowHealthyStep":0,"mRunStepCount":0,"mSpeed":5.00150728225708,"mStartTime":1655913000000,"mStepCount":364,"mTimeUnit":600000,"mTotalActiveTime":203547.44253711135,"mWalkStepCount":364},{"mCalorie":13.819609344005585,"mDistance":268.24437522888184,"mNowHealthyStep":0,"mRunStepCount":0,"mSpeed":5.5686259269714355,"mStartTime":1655913600000,"mStepCount":347,"mTimeUnit":600000,"mTotalActiveTime":173414.3733829036,"mWalkStepCount":347},{"mCalorie":3.2996289134025574,"mDistance":60.57624959945679,"mNowHealthyStep":0,"mRunStepCount":0,"mSpeed":4.731888771057129,"mStartTime":1655914200000,"mStepCount":83,"mTimeUnit":600000,"mTotalActiveTime":46086.14427489301,"mWalkStepCount":83},{"mCalorie":1.7199999690055847,"mDistance":31.580000400543213,"mNowHealthyStep":0,"mRunStepCount":0,"mSpeed":4.618103981018066,"mStartTime":1655914800000,"mStepCount":41,"mTimeUnit":600000,"mTotalActiveTime":24617.895419179215,"mWalkStepCount":41},{"mCalorie":5.799999952316284,"mDistance":104.88000059127808,"mNowHealthyStep":0,"mRunStepCount":0,"mSpeed":3.894035816192627,"mStartTime":1655915400000,"mStepCount":150,"mTimeUnit":600000,"mTotalActiveTime":96960.58794628312,"mWalkStepCount":150},{"mCalorie":4.660000026226044,"mDistance":86.92000007629395,"mNowHealthyStep":0,"mRunStepCount":0,"mSpeed":4.614439487457275,"mStartTime":1655916000000,"mStepCount":118,"mTimeUnit":600000,"mTotalActiveTime":67811.48860440905,"mWalkStepCount":118},{"mCalorie":5.099999874830246,"mDistance":91.63000059127808,"mNowHealthyStep":0,"mRunStepCount":0,"mSpeed":4.16019344329834,"mStartTime":1655916600000,"mStepCount":133,"mTimeUnit":600000,"mTotalActiveTime":79291.50985021517,"mWalkStepCount":133},{"mCalorie":7.679394572973251,"mDistance":132.14062356948853,"mNowHealthyStep":0,"mRunStepCount":1,"mSpeed":4.254413604736328,"mStartTime":1655917200000,"mStepCount":203,"mTimeUnit":600000,"mTotalActiveTime":111814.7643039942,"mWalkStepCount":202},{"mCalorie":26.679724514484406,"mDistance":496.63686180114746,"mNowHealthyStep":0,"mRunStepCount":0,"mSpeed":4.749255180358887,"mStartTime":1655917800000,"mStepCount":674,"mTimeUnit":600000,"mTotalActiveTime":376457.4937081286,"mWalkStepCount":674},{"mCalorie":39.25991654396057,"mDistance":736.9340629577637,"mNowHealthyStep":0,"mRunStepCount":0,"mSpeed":4.701559066772461,"mStartTime":1655918400000,"mStepCount":1014,"mTimeUnit":600000,"mTotalActiveTime":564272.9712993136,"mWalkStepCount":1014},{"mCalorie":11.609998911619186,"mDistance":220.7400040626526,"mNowHealthyStep":0,"mRunStepCount":0,"mSpeed":4.791833400726318,"mStartTime":1655919000000,"mStepCount":289,"mTimeUnit":600000,"mTotalActiveTime":165837.15926365167,"mWalkStepCount":289},{"mCalorie":0.0,"mDistance":0.0,"mNowHealthyStep":0,"mRunStepCount":0,"mSpeed":0.0,"mStartTime":1655919600000,"mStepCount":0,"mTimeUnit":600000,"mTotalActiveTime":0.0,"mWalkStepCount":0},{"mCalorie":0.8902148604393005,"mDistance":19.209688186645508,"mNowHealthyStep":0,"mRunStepCount":0,"mSpeed":6.169867515563965,"mStartTime":1655920200000,"mStepCount":26,"mTimeUnit":600000,"mTotalActiveTime":11208.48674044629,"mWalkStepCount":26},{"mCalorie":0.25,"mDistance":4.480000019073486,"mNowHealthyStep":0,"mRunStepCount":0,"mSpeed":4.0,"mStartTime":1655920800000,"mStepCount":6,"mTimeUnit":600000,"mTotalActiveTime":4032.0000171661377,"mWalkStepCount":6},{"mCalorie":0.0,"mDistance":0.0,"mNowHealthyStep":0,"mRunStepCount":0,"mSpeed":0.0,"mStartTime":1655921400000,"mStepCount":0,"mTimeUnit":600000,"mTotalActiveTime":0.0,"mWalkStepCount":0},{"mCalorie":0.0,"mDistance":0.0,"mNowHealthyStep":0,"mRunStepCount":0,"mSpeed":0.0,"mStartTime":1655922000000,"mStepCount":0,"mTimeUnit":600000,"mTotalActiveTime":0.0,"mWalkStepCount":0},{"mCalorie":0.0,"mDistance":0.0,"mNowHealthyStep":0,"mRunStepCount":0,"mSpeed":0.0,"mStartTime":1655922600000,"mStepCount":0,"mTimeUnit":600000,"mTotalActiveTime":0.0,"mWalkStepCount":0},{"mCalorie":1.7391992211341858,"mDistance":30.446874618530273,"mNowHealthyStep":0,"mRunStepCount":0,"mSpeed":4.327866554260254,"mStartTime":1655923200000,"mStepCount":46,"mTimeUnit":600000,"mTotalActiveTime":25326.276455256222,"mWalkStepCount":46},{"mCalorie":0.0,"mDistance":0.0,"mNowHealthyStep":0,"mRunStepCount":0,"mSpeed":0.0,"mStartTime":1655923800000,"mStepCount":0,"mTimeUnit":600000,"mTotalActiveTime":0.0,"mWalkStepCount":0},{"mCalorie":0.0,"mDistance":0.0,"mNowHealthyStep":0,"mRunStepCount":0,"mSpeed":0.0,"mStartTime":1655924400000,"mStepCount":0,"mTimeUnit":600000,"mTotalActiveTime":0.0,"mWalkStepCount":0},{"mCalorie":1.5399998724460602,"mDistance":26.829999923706055,"mNowHealthyStep":0,"mRunStepCount":0,"mSpeed":3.6405296325683594,"mStartTime":1655925000000,"mStepCount":37,"mTimeUnit":600000,"mTotalActiveTime":26531.305075293792,"mWalkStepCount":37},{"mCalorie":1.1900000274181366,"mDistance":22.40000057220459,"mNowHealthyStep":0,"mRunStepCount":0,"mSpeed":5.143834590911865,"mStartTime":1655925600000,"mStepCount":29,"mTimeUnit":600000,"mTotalActiveTime":15677.020708147345,"mWalkStepCount":29},{"mCalorie":0.0,"mDistance":0.0,"mNowHealthyStep":0,"mRunStepCount":0,"mSpeed":0.0,"mStartTime":1655926200000,"mStepCount":0,"mTimeUnit":600000,"mTotalActiveTime":0.0,"mWalkStepCount":0},{"mCalorie":2.189999967813492,"mDistance":38.110000133514404,"mNowHealthyStep":0,"mRunStepCount":0,"mSpeed":3.8472282886505127,"mStartTime":1655926800000,"mStepCount":52,"mTimeUnit":600000,"mTotalActiveTime":35660.99817595457,"mWalkStepCount":52},{"mCalorie":0.0,"mDistance":0.0,"mNowHealthyStep":0,"mRunStepCount":0,"mSpeed":0.0,"mStartTime":1655927400000,"mStepCount":0,"mTimeUnit":600000,"mTotalActiveTime":0.0,"mWalkStepCount":0},{"mCalorie":0.0,"mDistance":0.0,"mNowHealthyStep":0,"mRunStepCount":0,"mSpeed":0.0,"mStartTime":1655928000000,"mStepCount":0,"mTimeUnit":600000,"mTotalActiveTime":0.0,"mWalkStepCount":0},{"mCalorie":0.0,"mDistance":0.0,"mNowHealthyStep":0,"mRunStepCount":0,"mSpeed":0.0,"mStartTime":1655928600000,"mStepCount":0,"mTimeUnit":600000,"mTotalActiveTime":0.0,"mWalkStepCount":0},{"mCalorie":0.0,"mDistance":0.0,"mNowHealthyStep":0,"mRunStepCount":0,"mSpeed":0.0,"mStartTime":1655929200000,"mStepCount":0,"mTimeUnit":600000,"mTotalActiveTime":0.0,"mWalkStepCount":0},{"mCalorie":0.0,"mDistance":0.0,"mNowHealthyStep":0,"mRunStepCount":0,"mSpeed":0.0,"mStartTime":1655929800000,"mStepCount":0,"mTimeUnit":600000,"mTotalActiveTime":0.0,"mWalkStepCount":0},{"mCalorie":0.0,"mDistance":0.0,"mNowHealthyStep":0,"mRunStepCount":0,"mSpeed":0.0,"mStartTime":1655930400000,"mStepCount":0,"mTimeUnit":600000,"mTotalActiveTime":0.0,"mWalkStepCount":0},{"mCalorie":0.0,"mDistance":0.0,"mNowHealthyStep":0,"mRunStepCount":0,"mSpeed":0.0,"mStartTime":1655931000000,"mStepCount":0,"mTimeUnit":600000,"mTotalActiveTime":0.0,"mWalkStepCount":0},{"mCalorie":0.0,"mDistance":0.0,"mNowHealthyStep":0,"mRunStepCount":0,"mSpeed":0.0,"mStartTime":1655931600000,"mStepCount":0,"mTimeUnit":600000,"mTotalActiveTime":0.0,"mWalkStepCount":0},{"mCalorie":0.0,"mDistance":0.0,"mNowHealthyStep":0,"mRunStepCount":0,"mSpeed":0.0,"mStartTime":1655932200000,"mStepCount":0,"mTimeUnit":600000,"mTotalActiveTime":0.0,"mWalkStepCount":0},{"mCalorie":0.0,"mDistance":0.0,"mNowHealthyStep":0,"mRunStepCount":0,"mSpeed":0.0,"mStartTime":1655932800000,"mStepCount":0,"mTimeUnit":600000,"mTotalActiveTime":0.0,"mWalkStepCount":0},{"mCalorie":0.0,"mDistance":0.0,"mNowHealthyStep":0,"mRunStepCount":0,"mSpeed":0.0,"mStartTime":1655933400000,"mStepCount":0,"mTimeUnit":600000,"mTotalActiveTime":0.0,"mWalkStepCount":0},{"mCalorie":0.0,"mDistance":0.0,"mNowHealthyStep":0,"mRunStepCount":0,"mSpeed":0.0,"mStartTime":1655934000000,"mStepCount":0,"mTimeUnit":600000,"mTotalActiveTime":0.0,"mWalkStepCount":0},{"mCalorie":0.0,"mDistance":0.0,"mNowHealthyStep":0,"mRunStepCount":0,"mSpeed":0.0,"mStartTime":1655934600000,"mStepCount":0,"mTimeUnit":600000,"mTotalActiveTime":0.0,"mWalkStepCount":0}]