[{"calorie":0.0,"count":0,"distance":0.0,"speed":0.0},{"calorie":0.0,"count":0,"distance":0.0,"speed":0.0},{"calorie":0.0,"count":0,"distance":0.0,"speed":0.0},{"calorie":0.44999998807907104,"count":10,"distance":7.139999866485596,"speed":3.9000003337860107},{"calorie":0.9999511539936066,"count":27,"distance":21.040468215942383,"speed":5.208001136779785},{"calorie":0.0,"count":0,"distance":0.0,"speed":0.0},{"calorie":0.8999999761581421,"count":23,"distance":18.040000915527344,"speed":5.800000190734863},{"calorie":34.94999897480011,"count":873,"distance":662.9500007629395,"speed":4.732027053833008},{"calorie":44.56030082702637,"count":1114,"distance":863.7075042724609,"speed":5.195997714996338},{"calorie":1.8499608933925629,"count":45,"distance":33.37859392166138,"speed":4.212264537811279},{"calorie":0.0,"count":0,"distance":0.0,"speed":0.0},{"calorie":0.0,"count":0,"distance":0.0,"speed":0.0},{"calorie":0.0,"count":0,"distance":0.0,"speed":0.0},{"calorie":0.0,"count":0,"distance":0.0,"speed":0.0},{"calorie":0.0,"count":0,"distance":0.0,"speed":0.0},{"calorie":0.0,"count":0,"distance":0.0,"speed":0.0},{"calorie":0.0,"count":0,"distance":0.0,"speed":0.0},{"calorie":0.0,"count":0,"distance":0.0,"speed":0.0},{"calorie":0.0,"count":0,"distance":0.0,"speed":0.0},{"calorie":0.0,"count":0,"distance":0.0,"speed":0.0},{"calorie":0.0,"count":0,"distance":0.0,"speed":0.0},{"calorie":0.0,"count":0,"distance":0.0,"speed":0.0},{"calorie":0.0,"count":0,"distance":0.0,"speed":0.0},{"calorie":0.0,"count":0,"distance":0.0,"speed":0.0},{"calorie":0.0,"count":0,"distance":0.0,"speed":0.0},{"calorie":0.0,"count":0,"distance":0.0,"speed":0.0},{"calorie":0.0,"count":0,"distance":0.0,"speed":0.0},{"calorie":0.0,"count":0,"distance":0.0,"speed":0.0},{"calorie":0.0,"count":0,"distance":0.0,"speed":0.0},{"calorie":0.0,"count":0,"distance":0.0,"speed":0.0},{"calorie":0.0,"count":0,"distance":0.0,"speed":0.0},{"calorie":0.0,"count":0,"distance":0.0,"speed":0.0},{"calorie":0.0,"count":0,"distance":0.0,"speed":0.0},{"calorie":0.0,"count":0,"distance":0.0,"speed":0.0},{"calorie":0.0,"count":0,"distance":0.0,"speed":0.0},{"calorie":0.0,"count":0,"distance":0.0,"speed":0.0},{"calorie":0.0,"count":0,"distance":0.0,"speed":0.0},{"calorie":0.0,"count":0,"distance":0.0,"speed":0.0},{"calorie":0.0,"count":0,"distance":0.0,"speed":0.0},{"calorie":0.0,"count":0,"distance":0.0,"speed":0.0},{"calorie":0.0,"count":0,"distance":0.0,"speed":0.0},{"calorie":0.0,"count":0,"distance":0.0,"speed":0.0},{"calorie":0.0,"count":0,"distance":0.0,"speed":0.0},{"calorie":0.0,"count":0,"distance":0.0,"speed":0.0},{"calorie":0.0,"count":0,"distance":0.0,"speed":0.0},{"calorie":0.0,"count":0,"distance":0.0,"speed":0.0},{"calorie":1.8900002241134644,"count":46,"distance":34.41999816894531,"speed":4.181358337402344},{"calorie":0.0,"count":0,"distance":0.0,"speed":0.0},{"calorie":0.0,"count":0,"distance":0.0,"speed":0.0},{"calorie":0.0,"count":0,"distance":0.0,"speed":0.0},{"calorie":0.0,"count":0,"distance":0.0,"speed":0.0},{"calorie":0.0,"count":0,"distance":0.0,"speed":0.0},{"calorie":0.0,"count":0,"distance":0.0,"speed":0.0},{"calorie":0.0,"count":0,"distance":0.0,"speed":0.0},{"calorie":0.0,"count":0,"distance":0.0,"speed":0.0},{"calorie":0.0,"count":0,"distance":0.0,"speed":0.0},{"calorie":0.0,"count":0,"distance":0.0,"speed":0.0},{"calorie":0.0,"count":0,"distance":0.0,"speed":0.0},{"calorie":0.4599999785423279,"count":11,"distance":7.850000381469727,"speed":3.3173868656158447},{"calorie":0.0,"count":0,"distance":0.0,"speed":0.0},{"calorie":1.03000009059906,"count":25,"distance":18.559999465942383,"speed":4.344067573547363},{"calorie":10.469999074935913,"count":261,"distance":204.30002403259277,"speed":5.4523444175720215},{"calorie":25.929995834827423,"count":647,"distance":497.72997856140137,"speed":4.970351219177246},{"calorie":1.4299999475479126,"count":35,"distance":25.809999465942383,"speed":3.799999952316284},{"calorie":0.0,"count":0,"distance":0.0,"speed":0.0},{"calorie":0.0,"count":0,"distance":0.0,"speed":0.0},{"calorie":0.0,"count":0,"distance":0.0,"speed":0.0},{"calorie":0.6200000047683716,"count":15,"distance":11.75,"speed":6.099999904632568},{"calorie":0.0,"count":0,"distance":0.0,"speed":0.0},{"calorie":0.0,"count":0,"distance":0.0,"speed":0.0},{"calorie":2.099999189376831,"count":53,"distance":40.18999099731445,"speed":4.671678066253662},{"calorie":29.53999102115631,"count":738,"distance":565.3198757171631,"speed":4.93366813659668},{"calorie":12.909997463226318,"count":322,"distance":249.51993560791016,"speed":5.146197319030762},{"calorie":26.549994438886642,"count":665,"distance":514.1598262786865,"speed":5.114834785461426},{"calorie":12.230000019073486,"count":304,"distance":233.6600046157837,"speed":4.953265190124512},{"calorie":0.3999999761581421,"count":10,"distance":7.96999979019165,"speed":6.171220779418945},{"calorie":0.0,"count":0,"distance":0.0,"speed":0.0},{"calorie":0.6299999952316284,"count":15,"distance":11.029999732971191,"speed":3.757347822189331},{"calorie":0.0,"count":0,"distance":0.0,"speed":0.0},{"calorie":1.059999942779541,"count":26,"distance":19.829999923706055,"speed":4.72174072265625},{"calorie":3.4400002360343933,"count":84,"distance":64.34000444412231,"speed":4.934929847717285},{"calorie":0.0,"count":0,"distance":0.0,"speed":0.0},{"calorie":0.8600000143051147,"count":21,"distance":17.18000030517578,"speed":5.5},{"calorie":1.7200000286102295,"count":42,"distance":31.68000030517578,"speed":4.59192419052124},{"calorie":10.380047261714935,"count":241,"distance":198.22243309020996,"speed":6.368495941162109},{"calorie":0.0,"count":0,"distance":0.0,"speed":0.0},{"calorie":4.929999828338623,"count":100,"distance":84.37000274658203,"speed":6.700000286102295},{"calorie":15.779998451471329,"count":366,"distance":293.0300078392029,"speed":5.641859531402588},{"calorie":5.820000052452087,"count":137,"distance":107.39000463485718,"speed":5.309112071990967},{"calorie":1.860000193119049,"count":46,"distance":34.910003662109375,"speed":4.687783718109131},{"calorie":5.619941413402557,"count":140,"distance":106.95875120162964,"speed":4.783919334411621},{"calorie":1.5600000023841858,"count":39,"distance":30.06999969482422,"speed":5.065248489379883},{"calorie":13.809999734163284,"count":340,"distance":262.2200040817261,"speed":5.053905010223389},{"calorie":8.610000014305115,"count":213,"distance":162.2200002670288,"speed":4.840259075164795},{"calorie":9.14999994635582,"count":225,"distance":169.9699993133545,"speed":4.506569862365723},{"calorie":7.129999935626984,"count":175,"distance":134.52999877929688,"speed":5.060200214385986},{"calorie":1.6800000369548798,"count":39,"distance":28.271249771118164,"speed":4.104022979736328},{"calorie":6.40999972820282,"count":154,"distance":117.99000072479248,"speed":4.843994617462158},{"calorie":8.95999962091446,"count":222,"distance":168.9200096130371,"speed":4.814717769622803},{"calorie":17.640106737613678,"count":436,"distance":336.7987413406372,"speed":5.042279243469238},{"calorie":13.190244197845459,"count":327,"distance":247.83999252319336,"speed":4.77589225769043},{"calorie":8.18999981880188,"count":200,"distance":152.67000246047974,"speed":4.957207202911377},{"calorie":0.7100000083446503,"count":18,"distance":13.87000036239624,"speed":4.831658363342285},{"calorie":11.430185765028,"count":282,"distance":215.60015964508057,"speed":4.832001209259033},{"calorie":7.879999995231628,"count":196,"distance":149.75000286102295,"speed":5.035154819488525},{"calorie":8.200000077486038,"count":202,"distance":154.6700005531311,"speed":4.946183204650879},{"calorie":9.49016597867012,"count":233,"distance":172.42812490463257,"speed":4.220888614654541},{"calorie":9.480077862739563,"count":235,"distance":179.33078861236572,"speed":4.760443210601807},{"calorie":11.629999905824661,"count":289,"distance":223.89999771118164,"speed":5.1151628494262695},{"calorie":5.860000044107437,"count":144,"distance":108.82999897003174,"speed":4.769225597381592},{"calorie":9.099999994039536,"count":220,"distance":166.76000022888184,"speed":4.698011875152588},{"calorie":4.199999958276749,"count":104,"distance":79.8499984741211,"speed":5.079864501953125},{"calorie":7.210000038146973,"count":180,"distance":139.84999990463257,"speed":5.20345401763916},{"calorie":10.870000034570694,"count":266,"distance":206.36999893188477,"speed":5.0043768882751465},{"calorie":4.970175743103027,"count":123,"distance":95.91984367370605,"speed":5.328830242156982},{"calorie":9.39000004529953,"count":230,"distance":174.31000423431396,"speed":4.694764614105225},{"calorie":5.96999990940094,"count":147,"distance":111.3299970626831,"speed":4.5621418952941895},{"calorie":1.7799999713897705,"count":39,"distance":28.90999984741211,"speed":4.4590911865234375},{"calorie":10.370000064373016,"count":258,"distance":198.23000144958496,"speed":4.935367584228516},{"calorie":8.360351026058197,"count":208,"distance":159.06812715530396,"speed":4.860127925872803},{"calorie":4.080000102519989,"count":101,"distance":78.86000156402588,"speed":5.316280841827393},{"calorie":8.020019054412842,"count":165,"distance":137.10390186309814,"speed":6.006556987762451},{"calorie":7.980097413063049,"count":194,"distance":145.74078130722046,"speed":4.624965190887451},{"calorie":16.440458953380585,"count":403,"distance":311.58031463623047,"speed":5.139342308044434},{"calorie":6.390321969985962,"count":159,"distance":125.3778076171875,"speed":5.468088626861572},{"calorie":11.94028326869011,"count":294,"distance":225.7079701423645,"speed":4.922203063964844},{"calorie":0.550048828125,"count":10,"distance":7.65234375,"speed":6.78548526763916},{"calorie":3.2699999511241913,"count":77,"distance":59.75999927520752,"speed":5.627565383911133},{"calorie":1.7899999767541885,"count":44,"distance":33.730000376701355,"speed":4.954610347747803},{"calorie":0.0,"count":0,"distance":0.0,"speed":0.0},{"calorie":0.0,"count":0,"distance":0.0,"speed":0.0},{"calorie":0.0,"count":0,"distance":0.0,"speed":0.0},{"calorie":0.0,"count":0,"distance":0.0,"speed":0.0},{"calorie":0.0,"count":0,"distance":0.0,"speed":0.0},{"calorie":0.0,"count":0,"distance":0.0,"speed":0.0},{"calorie":0.0,"count":0,"distance":0.0,"speed":0.0},{"calorie":0.0,"count":0,"distance":0.0,"speed":0.0},{"calorie":0.0,"count":0,"distance":0.0,"speed":0.0},{"calorie":0.0,"count":0,"distance":0.0,"speed":0.0},{"calorie":0.0,"count":0,"distance":0.0,"speed":0.0},{"calorie":0.0,"count":0,"distance":0.0,"speed":0.0},{"calorie":0.0,"count":0,"distance":0.0,"speed":0.0},{"calorie":0.0,"count":0,"distance":0.0,"speed":0.0},{"calorie":0.0,"count":0,"distance":0.0,"speed":0.0}]